{"skeleton":{"hash":"Cc+eF5ItazlajgJf5Kxk/sG/PIE","spine":"3.8.99","images":"","audio":"D:/阿拆/wb/xq/2022冲鸭/月月需求/九天玄女项目/风眠第二批特效需求(1)/R-虎力大仙-a/虎力大仙导出"},"bones":[{"name":"root"},{"name":"skill","parent":"root","color":"ff9700ff"},{"name":"juqi","parent":"skill","color":"ff9700ff"}],"slots":[{"name":"images/skill/juqi/jq_02","bone":"juqi"}],"skins":[{"name":"default","attachments":{"images/skill/juqi/jq_02":{"images/skill/juqi/jq_03":{"x":34.09,"width":150,"height":150},"images/skill/juqi/jq_04":{"x":34.09,"width":150,"height":150},"images/skill/juqi/jq_05":{"x":34.09,"width":150,"height":150},"images/skill/juqi/jq_06":{"x":34.09,"width":150,"height":150},"images/skill/juqi/jq_07":{"x":34.09,"width":150,"height":150}}}}],"animations":{"animation":{"slots":{"images/skill/juqi/jq_02":{"color":[{"time":0.2333,"color":"ffffffff"},{"time":0.3667,"color":"ffffff00"}],"attachment":[{"time":0.1,"name":"images/skill/juqi/jq_03"},{"time":0.1333,"name":"images/skill/juqi/jq_04"},{"time":0.1667,"name":"images/skill/juqi/jq_05"},{"time":0.2,"name":"images/skill/juqi/jq_06"},{"time":0.2333,"name":"images/skill/juqi/jq_07"},{"time":0.3667,"name":null}]}},"bones":{"juqi":{"rotate":[{"time":0.2333},{"time":0.3667,"angle":-20}],"translate":[{"time":0.1,"x":-31.27,"y":64.35}],"scale":[{"time":0.1,"x":1.1,"y":1.1,"curve":"stepped"},{"time":0.2333,"x":1.1,"y":1.1},{"time":0.3667,"x":0.5,"y":0.5}]}}}}}