{"skeleton":{"hash":"df3k2IL1Jrd1jbtirlZvBmyg/Rg","spine":"3.8.99","images":"./images/","audio":""},"bones":[{"name":"root","scaleX":0.4843,"scaleY":0.4843},{"name":"elc8","parent":"root","length":27.13,"rotation":16.64,"x":252.62,"y":-41.44,"color":"007effff"},{"name":"ji3","parent":"root","x":305.53,"y":88.15,"scaleX":0.5697,"scaleY":0.5697,"color":"53ff00ff"},{"name":"ji4","parent":"root","x":340.77,"y":107.44,"scaleX":0.5697,"scaleY":0.5697,"color":"53ff00ff"},{"name":"ji5","parent":"root","x":360.06,"y":132.61,"scaleX":0.5697,"scaleY":0.5697,"color":"53ff00ff"},{"name":"113","parent":"root","x":472.34,"y":433.38},{"name":"115","parent":"113","x":-22.62,"y":-0.33},{"name":"116","parent":"113","x":-22.62,"y":-0.33},{"name":"117","parent":"113","x":-22.62,"y":-0.33}],"slots":[{"name":"elc8","bone":"elc8","blend":"additive"},{"name":"ji3","bone":"ji3","blend":"additive"},{"name":"ji8","bone":"ji3","blend":"additive"},{"name":"ji4","bone":"ji4","blend":"additive"},{"name":"ji6","bone":"ji4","blend":"additive"},{"name":"ji5","bone":"ji5","blend":"additive"},{"name":"ji7","bone":"ji5","blend":"additive"},{"name":"113","bone":"115","blend":"additive"},{"name":"114","bone":"116"},{"name":"115","bone":"117"}],"skins":[{"name":"default","attachments":{"113":{"113":{"x":-70.27,"y":1.48,"width":165,"height":295}},"114":{"113":{"x":-70.27,"y":1.48,"width":165,"height":295}},"115":{"113":{"x":-70.27,"y":1.48,"width":165,"height":295}},"elc8":{"elc1":{"rotation":-90,"width":200,"height":187},"elc2":{"rotation":-90,"width":200,"height":187},"elc3":{"rotation":-90,"width":200,"height":187},"elc4":{"rotation":-90,"width":200,"height":187},"elc5":{"rotation":-90,"width":200,"height":187},"elc6":{"rotation":-90,"width":200,"height":187},"elc7":{"rotation":-90,"width":200,"height":187},"elc8":{"rotation":-90,"width":200,"height":187}},"ji3":{"ji1":{"width":300,"height":300},"ji2":{"width":300,"height":300},"ji3":{"width":300,"height":300},"ji4":{"width":300,"height":300},"ji5":{"width":300,"height":300}},"ji4":{"ji1":{"width":300,"height":300},"ji2":{"width":300,"height":300},"ji3":{"width":300,"height":300},"ji4":{"width":300,"height":300},"ji5":{"width":300,"height":300}},"ji5":{"ji1":{"width":300,"height":300},"ji2":{"width":300,"height":300},"ji3":{"width":300,"height":300},"ji4":{"width":300,"height":300},"ji5":{"width":300,"height":300}},"ji6":{"ji1":{"width":300,"height":300},"ji2":{"width":300,"height":300},"ji3":{"width":300,"height":300},"ji4":{"width":300,"height":300},"ji5":{"width":300,"height":300}},"ji7":{"ji1":{"width":300,"height":300},"ji2":{"width":300,"height":300},"ji3":{"width":300,"height":300},"ji4":{"width":300,"height":300},"ji5":{"width":300,"height":300}},"ji8":{"ji1":{"width":300,"height":300},"ji2":{"width":300,"height":300},"ji3":{"width":300,"height":300},"ji4":{"width":300,"height":300},"ji5":{"width":300,"height":300}}}}],"events":{"K":{}},"animations":{"skill179":{"slots":{"elc8":{"attachment":[{"name":"elc1"},{"time":0.0333,"name":null},{"time":0.0667,"name":"elc2"},{"time":0.1,"name":null},{"time":0.1333,"name":"elc3"},{"time":0.1667,"name":null}]},"ji3":{"attachment":[{"name":"ji1"},{"time":0.0333,"name":"ji2"},{"time":0.0667,"name":"ji3"},{"time":0.1,"name":"ji4"},{"time":0.1333,"name":"ji5"},{"time":0.1667,"name":null}]},"ji4":{"attachment":[{"name":"ji1"},{"time":0.0333,"name":"ji2"},{"time":0.0667,"name":"ji3"},{"time":0.1,"name":"ji4"},{"time":0.1333,"name":"ji5"},{"time":0.1667,"name":null}]},"ji5":{"attachment":[{"name":"ji1"},{"time":0.0333,"name":"ji2"},{"time":0.0667,"name":"ji3"},{"time":0.1,"name":"ji4"},{"time":0.1333,"name":"ji5"},{"time":0.1667,"name":null}]},"ji6":{"attachment":[{"name":"ji1"},{"time":0.0333,"name":"ji2"},{"time":0.0667,"name":"ji3"},{"time":0.1,"name":"ji4"},{"time":0.1333,"name":"ji5"},{"time":0.1667,"name":null}]},"ji7":{"attachment":[{"name":"ji1"},{"time":0.0333,"name":"ji2"},{"time":0.0667,"name":"ji3"},{"time":0.1,"name":"ji4"},{"time":0.1333,"name":"ji5"},{"time":0.1667,"name":null}]},"ji8":{"attachment":[{"name":"ji1"},{"time":0.0333,"name":"ji2"},{"time":0.0667,"name":"ji3"},{"time":0.1,"name":"ji4"},{"time":0.1333,"name":"ji5"},{"time":0.1667,"name":null}]}},"bones":{"ji3":{"rotate":[{"angle":131.71}],"translate":[{"x":108.47,"y":342.84}],"scale":[{"x":1.531,"y":1.531}]},"ji4":{"rotate":[{"angle":-2.7}],"translate":[{"x":2.74,"y":368.82}],"scale":[{"x":1.531,"y":1.531}]},"ji5":{"rotate":[{"angle":-113.51}],"translate":[{"x":72.63,"y":393.91}],"scale":[{"x":1.531,"y":1.531}]},"elc8":{"rotate":[{"angle":-100.39},{"time":0.2,"angle":-158.65}],"translate":[{"x":137.77,"y":520.05}],"scale":[{"x":2.657,"y":1.935}]}},"drawOrder":[{}],"events":[{"time":0.3667,"name":"K"}]}}}