{"skeleton":{"hash":"P7lCqjsflyhLvN138L0Bf15Wzzo","spine":"3.8.99","x":-1166.76,"y":-125.58,"width":1559,"height":720,"images":"./images/","audio":""},"bones":[{"name":"root"},{"name":"bone2","parent":"root","scaleX":0.07,"scaleY":0.07},{"name":"bone","parent":"bone2","x":27.42,"y":342.98},{"name":"shenti","parent":"bone","length":146.14,"rotation":92.66,"x":47.42,"y":-34.61},{"name":"shenti2","parent":"shenti","length":112.32,"rotation":19.54,"x":145.39,"y":1.48},{"name":"tou","parent":"shenti2","length":227.31,"rotation":-28.2,"x":100.09,"y":-3.56},{"name":"idle","parent":"tou","rotation":7.53,"x":244.88,"y":-53.44},{"name":"weijin","parent":"shenti2","length":58.76,"rotation":153.51,"x":133.06,"y":53.06},{"name":"weijin2","parent":"weijin","length":39.27,"rotation":5.57,"x":65.26,"y":-0.39},{"name":"weijin3","parent":"weijin2","length":47.47,"rotation":-0.93,"x":39.27},{"name":"weijin4","parent":"weijin3","length":50.13,"rotation":-2.36,"x":48.05},{"name":"huzi1","parent":"tou","length":21.81,"rotation":129.92,"x":198.03,"y":-59.59},{"name":"huzi2","parent":"huzi1","length":40.69,"rotation":20.44,"x":23.28,"y":-0.61},{"name":"huzi3","parent":"huzi2","length":50.24,"rotation":18.67,"x":40.77,"y":0.44},{"name":"huzi4","parent":"huzi3","length":44.22,"rotation":8.04,"x":50.44,"y":0.39},{"name":"huzi5","parent":"huzi4","length":50.82,"rotation":1.45,"x":43.52,"y":-0.41},{"name":"huzi6","parent":"huzi5","length":45.4,"rotation":-10.14,"x":51.83,"y":0.13},{"name":"huzi7","parent":"huzi6","length":42.52,"rotation":-14.16,"x":45.4},{"name":"huzi8","parent":"tou","length":23.68,"rotation":-118.62,"x":216.55,"y":-152.4},{"name":"huzi9","parent":"huzi8","length":43.41,"rotation":-44.91,"x":25.5,"y":-1},{"name":"huzi10","parent":"huzi9","length":44.08,"rotation":-9.87,"x":44.78,"y":-0.25},{"name":"huzi11","parent":"huzi10","length":47.38,"rotation":2.2,"x":44.08},{"name":"huzi12","parent":"huzi11","length":46.86,"rotation":-2.81,"x":47.38},{"name":"huzi13","parent":"huzi12","length":50.83,"rotation":5.76,"x":46.86},{"name":"huzi14","parent":"huzi13","length":39.3,"rotation":17.17,"x":50.83},{"name":"zuobi1","parent":"shenti2","length":164.36,"rotation":140.39,"x":223.75,"y":228.64},{"name":"zuobi3","parent":"zuobi1","length":97.87,"rotation":2.18,"x":162.15,"y":-1.46},{"name":"zuoshou","parent":"zuobi3","length":71.29,"rotation":24.22,"x":97.14,"y":1.05},{"name":"weapon","parent":"zuoshou","length":52.12,"rotation":37.72,"x":25.14,"y":4.93},{"name":"shenti3","parent":"shenti2","length":141.66,"rotation":176.75,"x":43.83,"y":-130.19},{"name":"youbi2","parent":"shenti3","length":82.46,"rotation":-12.86,"x":141.99,"y":1.56},{"name":"youshou","parent":"youbi2","length":68.42,"rotation":0.25,"x":75.53,"y":1.27},{"name":"kuzi","parent":"bone","length":101.1,"rotation":-86.46,"x":-39.17,"y":-1.73},{"name":"kuzi2","parent":"kuzi","length":74.09,"rotation":11.83,"x":112.63,"y":99.49,"color":"72a07cff"},{"name":"kuzi3","parent":"kuzi","length":105.62,"rotation":-22.29,"x":92.29,"y":-84.45,"color":"72a07cff"},{"name":"2","parent":"bone2","length":100,"rotation":-22.91,"x":101.39,"y":82.56,"color":"ff3f00ff"},{"name":"youtui1","parent":"kuzi","length":75.89,"rotation":3.42,"x":116.07,"y":113.81},{"name":"youtui3","parent":"youtui1","length":79.09,"rotation":-19.61,"x":73.84,"y":-0.38},{"name":"1","parent":"bone2","length":100,"rotation":-22.91,"x":-136.94,"y":69.54,"color":"ff3f00ff"},{"name":"zuotui1","parent":"kuzi","length":64.87,"rotation":-3.54,"x":111.54,"y":-114.02},{"name":"zuotui3","parent":"zuotui1","length":89.03,"rotation":-11.77,"x":66.3,"y":1.61},{"name":"tou2","parent":"tou","rotation":7.53,"x":314.13,"y":264.73},{"name":"sheng1","parent":"tou2","length":65.25,"rotation":139.5,"x":37.98,"y":-5.83},{"name":"sheng2","parent":"sheng1","length":79.49,"rotation":0.38,"x":66.05,"y":-0.08},{"name":"sheng3","parent":"tou2","length":71.2,"rotation":149.24,"x":-22.59,"y":32.27},{"name":"sheng4","parent":"sheng3","length":66.52,"rotation":16.86,"x":72.69,"y":0.84},{"name":"sheng5","parent":"sheng4","length":74.53,"rotation":6.22,"x":69.43,"y":0.05},{"name":"weiba","parent":"kuzi","length":69.37,"rotation":-38.62,"x":55.94,"y":-141.86},{"name":"weiba2","parent":"weiba","length":82.8,"rotation":-31.73,"x":69.52,"y":0.84},{"name":"weiba3","parent":"weiba2","length":79.04,"rotation":-32.88,"x":82.8},{"name":"weiba4","parent":"weiba3","length":73.38,"rotation":-24.93,"x":79.24,"y":-1.19},{"name":"weiba5","parent":"weiba4","length":71.94,"rotation":-40.31,"x":74.07,"y":-0.99},{"name":"zuoshou3","parent":"zuoshou","length":19.27,"rotation":-105.6,"x":27.53,"y":61.78},{"name":"ballli","parent":"weapon","rotation":8.25,"x":417.28,"y":49.39,"scaleX":0.8546,"scaleY":0.8546},{"name":"bone4","parent":"bone2","x":-238.91,"y":-62.27},{"name":"weapon2","parent":"bone4","length":52.12,"rotation":-29.76,"x":-356.02,"y":207.38,"color":"d400ffff"}],"slots":[{"name":"weiba","bone":"weiba","attachment":"weiba"},{"name":"youshou","bone":"youshou","attachment":"youshou"},{"name":"youbi2","bone":"youbi2","attachment":"youbi2"},{"name":"youbi1","bone":"shenti3","attachment":"youbi1"},{"name":"youjiao","bone":"2","attachment":"youjiao"},{"name":"youjiao2","bone":"1","attachment":"youjiao"},{"name":"youtui2","bone":"youtui3","attachment":"youtui2"},{"name":"youtui1","bone":"youtui1","attachment":"youtui1"},{"name":"zuotui2b","bone":"zuotui3"},{"name":"zuotui1b","bone":"zuotui1"},{"name":"zuotui2","bone":"zuotui3","attachment":"zuotui2"},{"name":"zuotui1","bone":"zuotui1","attachment":"zuotui1"},{"name":"sheng2","bone":"sheng3","attachment":"sheng2"},{"name":"sheng1","bone":"sheng1","attachment":"sheng1"},{"name":"kuzi2","bone":"kuzi","attachment":"kuzi2"},{"name":"shenti","bone":"shenti","attachment":"shenti"},{"name":"kuzi","bone":"kuzi","attachment":"kuzi"},{"name":"yifu2","bone":"shenti2","attachment":"yifu2"},{"name":"tou","bone":"tou","attachment":"tou"},{"name":"yifu1","bone":"bone2","attachment":"yifu1"},{"name":"weijin","bone":"weijin","attachment":"weijin"},{"name":"smeil","bone":"idle"},{"name":"angry","bone":"idle"},{"name":"die","bone":"idle"},{"name":"hit","bone":"idle"},{"name":"idle","bone":"idle","attachment":"idle"},{"name":"huzi2","bone":"huzi8","attachment":"huzi2"},{"name":"huzi1","bone":"huzi1","attachment":"huzi1"},{"name":"zuoshou2","bone":"zuoshou3","attachment":"zuoshou2"},{"name":"weapon","bone":"weapon","attachment":"weapon"},{"name":"weapon3","bone":"weapon2"},{"name":"weapon2","bone":"weapon","blend":"additive"},{"name":"weapontx","bone":"weapon","blend":"additive"},{"name":"zuoshou","bone":"zuoshou","attachment":"zuoshou"},{"name":"zuobi2","bone":"zuobi3","attachment":"zuobi2"},{"name":"zuobi1","bone":"zuobi1","attachment":"zuobi1"},{"name":"ballli","bone":"ballli","blend":"additive"}],"ik":[{"name":"1","order":1,"bones":["zuotui1","zuotui3"],"target":"1","bendPositive":false},{"name":"2","bones":["youtui1","youtui3"],"target":"2","bendPositive":false}],"skins":[{"name":"default","attachments":{"angry":{"angry":{"x":-28.74,"y":47.34,"rotation":-91.52,"width":352,"height":213}},"ballli":{"ballli":{"x":-0.64,"y":2.05,"rotation":29.76,"width":148,"height":148}},"die":{"die":{"x":-36.9,"y":41.55,"rotation":-91.52,"width":366,"height":215}},"hit":{"hit":{"x":-45,"y":56.77,"rotation":-91.52,"width":366,"height":244}},"huzi1":{"huzi1":{"type":"mesh","uvs":[1,0,1,0.07059,0.89289,0.10745,0.8278,0.12985,0.74454,0.20295,0.65746,0.2794,0.61026,0.36439,0.53443,0.50092,0.52441,0.52574,0.45291,0.7028,0.42591,0.76968,0.33047,0.86546,0.29657,0.89948,0.1073,1,0,1,0,0.95451,0.14831,0.88114,0.17818,0.83901,0.27134,0.7076,0.28049,0.68365,0.34864,0.50541,0.40194,0.36599,0.41644,0.32806,0.51613,0.17798,0.54578,0.13336,0.71737,0.04489,0.80444,0,0.78646,0.05862,0.61699,0.18424,0.48676,0.35759,0.42601,0.51483,0.37706,0.7009,0.26694,0.85648],"triangles":[0,1,2,2,27,26,2,26,0,4,27,3,4,25,27,23,24,28,28,24,25,3,27,2,27,25,26,30,21,29,21,22,29,6,29,5,5,23,28,5,29,23,29,22,23,5,28,4,28,25,4,8,30,7,7,29,6,18,19,31,8,9,30,9,31,30,19,20,31,31,20,30,20,21,30,30,29,7,32,18,11,11,31,10,11,18,31,32,17,18,10,31,9,12,16,32,32,16,17,16,12,13,16,13,15,13,14,15,12,32,11],"vertices":[1,11,-6.99,-1.01,1,1,11,3.85,15.1,1,2,12,3.19,16.7,0.19936,11,20.43,16.16,0.80064,3,13,-22.16,21.58,0.01965,12,12.87,13.79,0.71638,11,30.52,16.8,0.26397,3,13,0.06,17.65,0.72015,12,35.17,17.18,0.27967,11,50.23,27.77,1.7E-4,2,14,-25.04,16.82,0.04026,13,23.29,13.55,0.95974,2,14,-1.05,14.72,0.9471,13,47.34,14.82,0.0529,1,14,37.49,11.33,1,1,14,44.42,11.17,1,2,16,-2.79,8.68,0.42314,15,50.61,9.17,0.57686,1,16,15.74,11.09,1,2,17,-2.89,7.39,0.29206,16,44.4,7.87,0.70794,2,17,7.26,8.77,0.98069,16,54.58,6.73,0.01931,1,17,43.02,3.55,1,1,17,49.97,-7.67,1,1,17,39.33,-14.26,1,2,17,12.57,-9.38,0.98842,16,55.29,-12.18,0.01158,2,17,0.79,-12.36,0.42994,16,43.14,-12.18,0.57006,2,16,5.23,-12.2,0.67016,15,54.83,-12.8,0.32984,2,16,-1.39,-13.12,0.20438,15,48.15,-12.54,0.79562,2,15,-1.54,-10.61,0.8179,14,42.25,-11.05,0.1821,2,14,3.36,-10.53,0.07894,13,55.24,-9.56,0.92106,1,13,44.75,-10.9,1,2,13,1.69,-11.22,0.02195,12,45.96,-9.65,0.97805,1,12,33.86,-13.84,1,2,12,1.79,-10.86,0.95398,11,28.75,-10.17,0.04602,1,11,12.97,-14.43,1,1,12,-0.09,-1.76,1,1,13,-0.28,1.15,1,1,13,49.99,-0.26,1,1,15,-0.21,-0.84,1,2,16,-0.47,-0.37,0.4252,15,51.31,-0.14,0.5748,2,17,-0.88,-0.55,0.331,16,44.41,-0.32,0.669],"hull":27,"edges":[0,2,24,26,26,28,28,30,30,32,0,52,48,50,50,52,2,4,4,6,44,46,46,48,6,8,8,10,10,12,12,14,42,44,40,42,14,16,16,18,18,20,36,38,38,40,32,34,34,36,20,22,22,24],"width":123,"height":275}},"huzi2":{"huzi2":{"type":"mesh","uvs":[0,0,0,0.04184,0.19693,0.10298,0.29118,0.22368,0.30369,0.35037,0.31999,0.51554,0.33655,0.68333,0.34193,0.73784,0.44275,0.85883,0.48693,0.91184,0.78418,1,1,1,1,0.94946,0.83493,0.89303,0.79022,0.84206,0.67543,0.71119,0.67805,0.68172,0.69214,0.52331,0.70672,0.35941,0.71893,0.22211,0.61743,0.07162,0.29843,0,0.46431,0.21442,0.43494,0.35669,0.49956,0.51547,0.50544,0.67807,0.61706,0.85209],"triangles":[2,1,0,21,2,0,22,21,20,3,2,21,22,20,19,22,3,21,23,4,3,22,23,3,18,22,19,23,22,18,5,4,23,24,23,18,5,23,24,17,24,18,25,24,17,6,5,24,16,25,17,6,24,25,15,25,16,7,6,25,26,25,15,26,15,14,8,7,25,8,25,26,9,8,26,10,26,14,10,14,13,9,26,10,13,12,11,10,13,11],"vertices":[1,18,-3.12,2.75,1,2,19,-10.74,-19.8,0.00551,18,3.92,-7.44,0.99449,2,19,9.35,-10.69,0.86167,18,24.57,-15.17,0.13833,2,20,2.67,-10.7,0.70706,19,45.58,-11.25,0.29294,2,21,-4.3,-10.14,0.19659,20,40.18,-10.29,0.80341,2,22,-2.23,-11.61,0.33304,21,44.59,-11.49,0.66696,2,23,-0.49,-10.56,0.54205,22,47.43,-10.55,0.45795,1,23,15.59,-11.83,1,2,24,-1.66,-8.91,0.48928,23,51.87,-9.01,0.51072,1,24,13.89,-12.43,1,1,24,45.33,-5.07,1,1,24,50.72,7.65,1,1,24,36.94,13.48,1,2,24,17.44,10.26,0.99717,23,64.47,14.95,0.00283,2,24,2.43,13.5,0.51531,23,49.17,13.62,0.48469,2,23,9.89,10.19,0.96857,22,55.68,11.14,0.03143,2,23,1.23,11.24,0.56412,22,46.96,11.3,0.43588,2,22,0.07,12.21,0.52895,21,48.05,12.19,0.47105,2,21,-0.36,15.5,0.45125,20,43.12,15.47,0.54875,2,20,2.5,16.68,0.58801,19,50.1,15.75,0.41199,2,19,5.11,17.46,0.99025,18,41.45,7.75,0.00975,1,18,12.6,13.6,1,2,20,0.05,0.41,0.94808,19,44.9,0.14,0.05192,2,21,-2.02,-1.84,0.17273,20,42.14,-1.91,0.82727,2,22,-2.25,-0.12,0.08723,21,45.13,-0.01,0.91277,2,23,-0.96,0.35,0.32228,22,45.88,0.26,0.67772,2,24,0.85,2.14,0.60859,23,51.01,2.29,0.39141],"hull":22,"edges":[0,2,2,4,4,6,18,20,20,22,22,24,24,26,38,40,40,42,0,42,6,8,36,38,8,10,34,36,10,12,12,14,30,32,32,34,14,16,16,18,26,28,28,30],"width":64,"height":296}},"idle":{"idle":{"type":"mesh","uvs":[1,0.70493,1,0.7928,1,0.86875,0.86448,0.94305,0.62469,1,0.13712,1,0,1,0,0,1,0,0.1742,0.90083,0.55692,0.73364,0.83432,0.66272,0.37865,0.93961,0.61523,0.81726,0.83695,0.75275],"triangles":[8,10,7,11,8,0,11,10,8,14,11,0,13,10,11,14,0,1,14,13,11,3,14,1,9,7,10,12,9,10,12,10,13,2,3,1,6,7,9,5,6,9,5,9,12,4,13,14,4,14,3,12,13,4,5,12,4],"vertices":[-65.08,-127.76,-82.3,-127.3,-97.18,-126.9,-110.47,-78.83,-119.38,5.84,-114.81,177.41,-113.53,225.66,82.4,220.44,73.04,-131.43,-95.73,163.84,-66.56,28.3,-55.26,-69.68,-105.24,92.1,-83.49,8.22,-72.92,-70.14],"hull":9,"edges":[12,14,14,16,12,18,18,20,20,22,0,16,22,0,4,6,6,8,8,10,10,12,10,24,24,26,26,28,0,2,2,4,28,2],"width":352,"height":196}},"kuzi":{"kuzi":{"type":"mesh","uvs":[0.02975,0,0.03219,0.18531,0.03463,0.33258,0.00536,0.52894,0,0.84156,0.14196,0.95783,0.33588,1,0.63226,1,0.7591,0.93716,0.94693,0.85965,1,0.70721,1,0.59095,0.97376,0.27316,1,0.05613,0.96279,0,0.82375,0.11297,0.53591,0.15689,0.24685,0.10522,0.51369,0.42581,0.82858,0.38963,0.75066,0.58635,0.3888,0.56374],"triangles":[21,3,2,4,3,21,5,4,21,6,5,21,7,6,21,20,19,11,20,11,10,9,20,10,8,20,9,20,7,21,7,20,8,2,1,17,18,21,2,19,12,11,18,17,16,18,16,19,2,17,18,15,14,13,12,15,13,19,15,12,16,15,19,20,18,19,21,18,20,1,0,17],"vertices":[1,32,-55.03,-261.61,1,1,32,-9.64,-263.15,1,1,32,26.45,-264.12,1,2,33,-116.55,-365.62,3.6E-4,34,57.65,-190.15,0.99964,2,33,-43.43,-388.62,1.8E-4,34,131.08,-168.17,0.99982,2,33,3.57,-325.13,8.0E-5,34,134.38,-89.25,0.99992,3,32,199.33,-118.18,0.0062,33,40.22,-230.82,4.1E-4,34,111.83,9.38,0.99339,3,32,208.84,35.34,0.38694,33,81.01,-82.51,0.51371,34,62.41,155.04,0.09935,3,32,197.54,102,0.03525,33,83.62,-14.95,0.96205,34,26.68,212.44,0.0027,2,33,91.15,84.08,0.99999,34,-22.63,298.65,1.0E-5,2,33,62.45,120.54,0.99996,34,-66.84,312.74,4.0E-5,2,33,34.98,128.09,0.99993,34,-93.82,303.58,7.0E-5,1,32,42.06,223.26,1,1,32,-10.17,240.13,1,1,32,-25.09,221.71,1,1,32,-1.93,147.97,1,1,32,-0.42,-1.8,1,1,32,-22.33,-150.75,1,1,32,64.62,-17.38,1,1,32,65.88,146.29,1,2,33,-0.42,3.61,1,34,-53.31,180.67,0,2,32,94.34,-84.16,0.00344,34,1.79,1.05,0.99656],"hull":18,"edges":[0,2,2,4,4,6,6,8,8,10,10,12,12,14,14,16,16,18,18,20,20,22,22,24,24,26,26,28,28,30,30,32,32,34,0,34,4,36,36,38,38,24],"width":519,"height":245}},"kuzi2":{"kuzi2":{"x":-9.44,"y":207.53,"rotation":86.46,"width":39,"height":29}},"sheng1":{"sheng1":{"type":"mesh","uvs":[0.08442,0.60197,0.20311,0.44793,0.18841,0.23937,0.17003,0,0.76184,0,1,0.04529,1,0.23068,0.94196,0.45662,0.83221,0.60277,0.67969,0.80589,0.53394,1,0.27295,1,0,0.9172,0,0.71154,0.50453,0.49139,0.55843,0.45025],"triangles":[14,0,1,8,14,15,8,15,7,14,1,15,7,15,6,15,4,6,4,15,2,15,1,2,2,3,4,4,5,6,9,10,14,11,13,0,11,0,14,10,11,14,11,12,13,9,14,8],"vertices":[2,43,50.79,-32.83,0.68,42,117.05,-32.58,0.32,1,42,84.19,-37.03,1,1,42,55.7,-62.82,1,1,42,23.13,-92.6,1,1,42,-30.84,-25.88,1,1,42,-46.08,6.21,1,1,42,-19.56,27.66,1,2,43,-47.68,47.67,0.0011,42,18.06,47.27,0.9989,2,43,-16.74,52.01,0.84,42,48.97,51.81,0.16,2,43,26.27,58.04,0.89115,42,91.94,58.12,0.10885,2,43,67.37,63.8,0.94004,42,133,64.15,0.05996,2,43,90.97,34.22,0.9938,42,156.8,34.73,0.0062,1,43,103.75,-6.22,1,1,43,74.18,-29.82,1,1,42,62.92,1.98,1,1,42,52.12,3.29,1],"hull":14,"edges":[2,4,4,6,6,8,8,10,10,12,12,14,20,22,22,24,24,26,14,16,2,30,30,14,2,0,0,26,16,18,18,20],"width":145,"height":184}},"sheng2":{"sheng2":{"type":"mesh","uvs":[1,0.07421,0.91981,0.31977,0.82511,0.59629,0.81765,0.67482,0.80707,0.78613,0.81158,1,0.45535,1,0,0.90376,0,0.71804,0.07383,0.57315,0.15774,0.4085,0.24006,0.30515,0.3336,0.1877,0.60416,0,0.82962,0,0.5726,0.32389,0.44183,0.6066],"triangles":[4,16,3,16,7,8,6,16,4,16,8,9,6,7,16,6,4,5,2,15,1,16,15,2,16,11,15,10,11,16,9,10,16,3,16,2,1,14,0,15,12,13,15,14,1,14,15,13,15,11,12],"vertices":[1,44,-2.39,13.89,1,2,44,52.42,34.63,0.61879,45,-9.6,38.23,0.38121,2,45,56.34,42.22,0.70007,46,-8.45,43.33,0.29993,2,45,74.61,45.4,0.37118,46,10.07,44.52,0.62882,2,45,100.52,49.91,0.0762,46,36.31,46.19,0.9238,1,46,86.44,52.08,1,1,46,90.56,13.83,1,1,46,73.24,-37.5,1,2,45,103.49,-38.67,0.0529,46,29.66,-42.19,0.9471,2,45,68.38,-38.21,0.60817,46,-5.19,-37.92,0.39183,2,44,110.88,-26.96,0.02672,45,28.49,-37.68,0.97328,2,44,85.26,-31.11,0.42803,45,2.76,-34.22,0.57197,2,44,56.14,-35.83,0.97822,45,-26.48,-30.29,0.02178,1,44,3.21,-31.97,1,1,44,-8.68,-10.72,1,2,44,71.58,2.39,0.38969,45,-0.61,1.81,0.61031,2,45,67.58,2.3,0.56828,46,-1.59,2.44,0.43172],"hull":15,"edges":[0,2,2,4,8,10,10,12,12,14,14,16,24,26,26,28,0,28,16,18,18,20,20,22,22,24,4,6,6,8],"width":108,"height":236}},"shenti":{"shenti":{"type":"mesh","uvs":[0.94004,0.01561,1,0.28861,1,0.60386,1,0.84761,0.92517,1,0.58946,1,0.09228,1,0,0.79561,0,0.53885,0,0.19436,0.09865,0,0.38761,0,0.27606,0.81757,0.63588,0.83612,0.90676,0.81448,0.86027,0.49909,0.86633,0.3352,0.41352,0.27955,0.41958,0.48053,0.69451,0.5702],"triangles":[16,17,11,0,16,11,16,0,1,19,18,17,17,16,19,18,8,9,15,19,16,15,16,1,2,15,1,19,15,14,9,17,18,17,10,11,17,9,10,13,18,19,18,7,8,14,15,2,12,7,18,13,19,14,12,18,13,14,2,3,6,7,12,5,12,13,6,12,5,4,14,3,13,14,4,5,13,4],"vertices":[1,4,85.48,-152.39,1,2,3,142.84,-157.74,0.01271,4,-1.2,-146.82,0.98729,2,3,71.04,-127.64,0.53,4,-65.11,-126.22,0.47,1,3,22.97,-129.66,1,1,3,-21.69,-92.75,1,2,3,-14.35,64,0.98669,4,-157.25,56.63,0.01331,2,3,-3.48,294.31,0.99746,4,-157.74,288.29,0.00254,2,3,64.09,335.78,0.96774,4,-91.97,332.43,0.03226,2,3,174.23,335.43,0.71,4,16.43,330.44,0.29,2,3,330.8,304.07,0.32,4,164.75,296.25,0.68,1,4,237.7,208.06,1,1,4,186.93,83.65,1,2,3,47.71,206.19,0.83283,4,-23.59,225.59,0.16717,2,3,34.31,39.31,0.67369,4,-92.03,72.81,0.32631,2,3,35.04,-86.82,0.85824,4,-133.53,-46.3,0.14176,2,3,131.82,-69.67,0.2487,4,-36.59,-62.51,0.7513,2,3,181.46,-74.8,0.14711,4,8.47,-83.95,0.85289,2,3,208.13,134.75,0.15618,4,103.7,104.61,0.84382,2,3,146.96,134.77,0.29369,4,46.06,125.09,0.70631,2,3,113.8,8.33,0.35625,4,-27.48,17.02,0.64375],"hull":12,"edges":[0,2,2,4,4,6,6,8,8,10,10,12,12,14,18,20,20,22,0,22,14,16,16,18],"width":465,"height":304}},"smeil":{"smeil":{"x":-31.76,"y":46.92,"rotation":-91.52,"width":353,"height":219}},"tou":{"tou":{"type":"mesh","uvs":[1,0.70867,0.935,0.84285,0.8002,0.94886,0.66772,1,0,1,0,0,0.4722,0,1,0,0.72694,0.21544,0.7252,0.41954,0.81532,0.5536,0.50968,0.66171,0.78858,0.57852,0.96289,0.57986,0.95243,0.62414,0.8432,0.65366,0.61311,0.68184,0.82809,0.73819,0.7421,0.92605,0.81414,0.8348],"triangles":[8,6,7,9,6,8,8,13,9,10,9,13,12,9,10,7,13,8,0,13,7,12,10,13,13,15,12,14,15,13,11,6,9,11,9,12,16,11,12,16,12,15,14,13,0,17,16,15,19,16,17,15,0,17,0,15,14,1,17,0,19,17,1,18,16,19,2,18,19,2,19,1,11,4,5,11,5,6,3,16,18,11,16,3,4,11,3,3,18,2],"vertices":[130.13,-214.77,63.44,-186.16,6,-118.33,-25.56,-49.05,-63.61,312.86,405.81,362.22,432.71,106.28,462.79,-179.79,346.1,-42.42,250.2,-51.56,192.4,-107.02,124.24,53.31,179.18,-93.75,188.48,-188.3,167.1,-184.82,147.02,-127.07,120.68,-3.74,106.48,-123.05,13.4,-85.71,60.33,-120.26],"hull":8,"edges":[8,10,10,12,12,14,12,16,16,18,18,20,22,24,24,26,28,30,30,32,0,14,0,2,2,4,6,8,4,6],"width":545,"height":472}},"weapon":{"weapon":{"x":121.05,"y":3.73,"rotation":37.89,"width":579,"height":392}},"weapon2":{"weapon":{"x":121.05,"y":3.73,"rotation":37.89,"width":579,"height":392}},"weapon3":{"weapon":{"x":117.62,"y":-6.62,"rotation":29.64,"width":579,"height":392}},"weapontx":{"weapontx":{"x":132.26,"y":39.89,"rotation":38.01,"width":755,"height":522}},"weiba":{"weiba":{"type":"mesh","uvs":[1,0.2417,0.85824,0,0.76882,0,0.68853,0.08454,0.57905,0.25711,0.44568,0.28247,0.30351,0.3095,0.29024,0.17713,0.27249,0,0.10096,0,0,0.10919,0,0.40811,0.05351,0.62074,0.20679,0.81488,0.3692,0.99054,0.56262,1,0.78342,1,0.9294,0.7625,1,0.47282,0.81079,0.5098,0.58452,0.66697,0.34183,0.62382,0.16665,0.3927],"triangles":[9,7,10,7,9,8,22,7,6,22,10,7,11,10,22,12,11,22,22,6,21,21,6,5,12,22,21,21,5,20,13,12,21,14,21,20,13,21,14,15,14,20,20,4,19,5,4,20,17,19,18,20,19,17,16,15,20,17,16,20,1,3,2,3,1,0,18,19,0,0,4,3,19,4,0],"vertices":[2,47,-12,22.34,0.98317,48,-80.64,-24.58,0.01683,2,47,-23.8,-43.28,0.99716,50,-73.12,-196.07,0.00284,4,47,-6.8,-67.5,0.98824,48,-28.97,-98.27,1.2E-4,49,-40.53,-143.2,0.00147,50,-48.76,-179.26,0.01017,4,47,22.03,-79.73,0.93073,48,1.98,-93.51,0.02116,49,-17.11,-122.4,0.0156,50,-36.3,-150.53,0.0325,5,47,70.54,-89.96,0.47189,48,48.62,-76.69,0.1927,49,12.92,-82.96,0.14766,50,-25.68,-102.11,0.18732,51,-10.65,-141.63,4.3E-4,5,47,99.97,-123.23,0.10433,48,91.15,-89.51,0.08109,49,55.6,-70.64,0.18304,50,7.83,-72.95,0.59938,51,-3.96,-97.72,0.03216,5,47,131.35,-158.7,0.00637,48,136.49,-103.18,0.0025,49,101.1,-57.51,0.0028,50,43.56,-41.86,0.56284,51,3.17,-50.9,0.4255,3,47,112.64,-177.2,2.1E-4,50,61.91,-60.72,0.09909,51,29.36,-53.41,0.90069,2,50,86.46,-85.96,1.1E-4,51,64.41,-56.77,0.99989,1,51,79.19,-1.95,1,1,51,67.22,35.88,1,3,49,196.88,-21.57,0.00563,50,115.27,31.1,0.27177,51,10.66,51.13,0.7226,3,49,172.42,16.54,0.10885,50,77.02,55.35,0.75956,51,-34.19,44.87,0.13159,2,49,116.01,45.52,0.7775,50,13.65,57.85,0.2225,1,49,57.23,70.42,1,2,48,110.97,55,0.31234,49,-6.2,61.48,0.68766,2,48,43.8,83.79,0.97787,49,-78.24,49.2,0.02213,2,47,84.97,61.87,0.01188,48,-18.95,60.04,0.98812,2,47,25.08,48.37,0.66888,48,-62.8,17.06,0.33112,2,47,67,1.28,0.57429,48,-2.38,-0.95,0.42571,4,47,135.24,-42.31,0.00152,48,78.6,-2.14,0.90371,49,-2.37,-4.08,0.09327,50,-72.79,-37.02,0.0015,1,49,78.24,1.09,1,2,50,71.58,-2.71,0.17574,51,-0.79,-2.92,0.82426],"hull":19,"edges":[0,2,2,4,4,6,6,8,16,18,18,20,20,22,22,24,24,26,26,28,28,30,30,32,32,34,34,36,0,36,8,10,10,12,12,14,14,16],"width":331,"height":196}},"weijin":{"weijin":{"type":"mesh","uvs":[0.40919,0,0.23713,0.05162,0.08204,0.24457,0,0.38291,0,0.54309,0.15958,0.67597,0.19109,0.8671,0.34618,1,0.57639,1,0.8478,1,0.83569,0.77973,1,0.60862,1,0.43024,0.97139,0.23547,0.76541,0.09895,0.64182,0,0.50369,0.31192,0.49885,0.51761,0.5255,0.75061],"triangles":[12,10,18,6,5,18,7,6,18,8,18,10,7,18,8,8,10,9,16,0,15,16,15,14,16,1,0,16,2,1,12,16,13,16,14,13,17,2,16,5,3,2,5,4,3,2,17,5,16,12,17,18,17,12,5,17,18,11,10,12],"vertices":[1,7,-3.79,-20.57,1,1,7,9.48,-47.7,1,2,8,-18.81,-67.87,0.37,7,53.12,-69.77,0.63,3,9,-27.04,-82.36,0.38193,8,10.9,-81.91,0.50148,7,84.06,-80.86,0.1166,3,9,7.72,-82.58,0.59,8,45.65,-82.69,0.39007,7,118.72,-78.26,0.01993,3,9,36.71,-56.74,0.83658,8,75.06,-57.33,0.14441,10,-8.99,-57.16,0.01901,3,9,78.22,-51.87,0.56536,8,116.64,-53.13,0.00443,10,32.28,-50.57,0.43021,2,9,107.21,-26.76,0.11298,10,60.21,-24.3,0.88702,2,9,107.44,10.76,0.00131,10,58.9,13.2,0.99869,2,9,107.72,55,0.06099,10,57.35,57.42,0.93901,4,9,59.91,53.32,0.52698,8,100.04,52.34,0.03194,7,159.74,61.41,0.00168,10,9.65,53.77,0.4394,4,9,22.94,80.33,0.68953,8,63.51,79.95,0.23225,7,120.71,85.34,0.057,10,-28.4,79.23,0.02123,3,9,-15.77,80.57,0.39107,8,24.81,80.81,0.37998,7,82.11,82.45,0.22895,1,7,40.31,74.64,1,1,7,13.28,38.94,1,1,7,-6.62,17.25,1,1,7,62.56,-0.14,1,2,9,2.69,-1.23,0.97401,8,41.94,-1.28,0.02599,1,10,5.1,3.02,1],"hull":16,"edges":[0,2,2,4,4,6,6,8,8,10,10,12,12,14,14,16,16,18,18,20,20,22,22,24,24,26,26,28,28,30,0,30],"width":163,"height":217}},"yifu1":{"yifu1":{"type":"mesh","uvs":[0.05093,0,0.02737,0.24315,0,0.48256,0,0.67145,0,0.90647,0.14906,1,0.5136,1,0.53556,0.88914,0.4587,0.51853,0.58087,0.64729,0.76123,0.68234,0.90151,0.57791,0.90477,0.9605,1,0.91526,1,0.77469,1,0.62533,1,0.37713,0.96165,0.21679,0.785,0.24974,0.39899,0.19483,0.11243,0],"triangles":[5,3,2,11,15,14,5,4,3,12,11,14,13,12,14,5,8,7,6,5,7,8,19,18,16,11,18,16,18,17,11,16,15,9,8,18,10,9,18,11,10,18,1,0,20,19,1,20,2,19,8,19,2,1,2,8,5],"vertices":[2,4,342.08,262.88,0.99951,3,525.29,271.32,4.9E-4,2,4,268.11,308.94,0.97246,3,446.69,322.35,0.02754,2,4,189.22,358.27,0.90304,3,362.66,375.57,0.09696,2,4,63.61,397.63,0.46,3,227.04,407.23,0.54,1,3,76.99,406.41,1,1,3,41.7,323.89,1,1,3,32.17,118.51,1,2,4,-37.75,122.62,0.19261,3,68.8,104.41,0.80739,2,4,93.92,115.7,0.83656,3,195.2,141.93,0.16344,2,4,25.45,69.3,0.91815,3,177.87,73.01,0.08185,2,4,-21.51,-21.48,0.63413,3,132.31,-25.96,0.36587,2,4,-18.91,-107.99,0.63872,3,163.69,-106.62,0.36128,1,3,35.19,-102.49,1,1,3,47.88,-156.85,1,2,4,-53.15,-157.83,0.21974,3,80.13,-157.35,0.78026,2,4,-19.92,-160.85,0.45321,3,115.99,-165.17,0.54679,2,4,33.71,-182.78,0.84119,3,176.61,-195.59,0.15881,2,4,87.91,-181.5,0.8949,3,235.39,-196.86,0.1051,2,4,109.21,-87.08,0.96174,3,262.84,-97.14,0.03826,2,4,207.35,105.8,0.99995,3,375.38,106.86,5.0E-5,1,4,329.02,230.7,1],"hull":21,"edges":[0,2,2,4,4,6,6,8,8,10,32,34,34,36,36,38,38,40,0,40,30,32,26,28,28,30,18,16,16,14,10,12,14,12,18,20,20,22,24,26,22,24],"width":564,"height":336}},"yifu2":{"yifu2":{"x":330.84,"y":232.5,"rotation":-112.2,"width":53,"height":46}},"youbi1":{"youbi1":{"type":"mesh","uvs":[1,0.28762,1,0.42223,0.91403,0.5515,0.96706,0.70749,0.92451,0.81936,0.86168,0.92055,0.73165,0.97226,0.63692,1,0.38514,1,0.19433,0.9371,0.12174,0.82788,0.05951,0.71644,0,0.53702,0,0.31486,0.20408,0,0.5657,0,0.65119,0.8006,0.77507,0.66629,0.57596,0.71198,0.22751,0.73316],"triangles":[4,16,3,5,16,4,6,16,5,16,7,8,6,7,16,14,15,0,18,12,13,14,0,1,13,14,1,17,2,3,17,18,2,12,19,11,13,1,2,13,2,18,18,19,12,16,18,17,16,17,3,10,11,19,16,10,19,16,19,18,9,10,16,8,9,16],"vertices":[2,29,55.66,69.39,0.99711,30,-99.26,46.92,0.00289,2,29,81.25,60.6,0.9736,30,-72.35,44.05,0.0264,2,29,102.81,43.38,0.83992,30,-47.5,32.06,0.16008,2,29,134.33,38.62,0.30877,30,-15.72,34.43,0.69123,2,29,154.1,26.98,0.01773,30,6.16,27.47,0.98227,1,30,25.66,18.57,1,1,30,34.51,3.5,1,2,29,178.36,-14.19,0.07446,30,38.97,-7.26,0.92554,2,29,169.53,-39.91,0.55834,30,36.08,-34.3,0.44166,2,29,150.88,-55.3,0.8396,30,21.32,-53.45,0.1604,2,29,127.57,-55.58,0.97253,30,-1.34,-58.92,0.02747,1,29,104.2,-54.67,1,1,29,68.01,-49.04,1,1,29,25.77,-34.54,1,1,29,-26.93,6.86,1,1,29,-14.25,43.8,1,2,29,140.95,0.28,0.86494,30,-0.72,-1.48,0.13506,2,29,119.76,21.7,0.654,30,-26.15,14.69,0.346,1,29,121.47,-1.62,1,2,29,113.27,-38.6,0.99981,30,-19.06,-45.54,1.9E-4],"hull":16,"edges":[32,10,10,12,12,14,2,4,4,34,34,36,36,38,38,22,22,24,22,20,20,32,32,18,18,20,14,16,18,16,6,32,4,6,8,10,6,8,2,0,30,0,28,30,24,26,28,26],"width":108,"height":201}},"youbi2":{"youbi2":{"type":"mesh","uvs":[0.7986,0.08553,0.87002,0.20328,0.92597,0.36714,0.95864,0.47247,1,0.68893,1,0.83888,0.9215,0.89131,0.79298,1,0.5721,1,0.36653,0.97319,0.25718,0.84719,0.09754,0.5578,0.04606,0.44892,0,0.26149,0,0.15073,0.12378,0.04411,0.33373,0,0.54586,0,0.5872,0.38649,0.65322,0.82663,0.44517,0.13416,0.60094,0.55493,0.68978,0.93563],"triangles":[6,19,5,22,19,6,7,22,6,8,22,7,1,18,20,18,1,2,18,2,3,21,18,3,21,11,18,21,3,4,19,21,4,19,4,5,10,11,21,10,21,19,9,10,19,8,9,19,22,8,19,20,16,17,20,17,0,20,13,14,1,20,0,15,16,20,15,20,14,18,13,20,12,13,18,11,12,18],"vertices":[2,29,100.11,39.8,0.74113,30,-49.34,27.97,0.25887,2,29,121.41,40.57,0.42479,30,-28.74,33.45,0.57521,3,29,149.54,37.24,0.01611,30,-0.57,36.47,0.97481,31,-75.95,35.53,0.00908,2,30,17.5,38.06,0.94182,31,-57.87,37.04,0.05818,2,30,54.34,38.58,0.47164,31,-21.03,37.4,0.52836,2,30,79.54,35.89,0.04474,31,4.16,34.61,0.95526,2,30,87.46,26.6,0.00155,31,12.04,25.28,0.99845,2,30,104.27,10.98,0.00212,31,28.78,9.58,0.99788,2,30,101.76,-12.52,0.49573,31,26.17,-13.91,0.50427,3,29,226.98,-52.63,0.00733,30,94.92,-33.92,0.95155,31,19.24,-35.27,0.04113,2,29,203.04,-56.78,0.06136,30,72.51,-43.29,0.93864,2,29,151.24,-57.06,0.66663,30,22.07,-55.09,0.33337,2,29,132.05,-56.29,0.89933,30,3.18,-58.62,0.10067,2,29,100.49,-50.67,0.99988,30,-28.83,-60.16,1.2E-4,1,29,82.78,-44.59,1,1,29,70.04,-26.22,1,1,29,70.28,-2.55,1,2,29,77.65,18.92,0.97412,30,-66.58,2.61,0.02588,1,30,-1.17,0.08,1,2,29,213.51,-15.57,1.1E-4,30,73.55,-0.79,0.99989,2,29,95.6,1.37,0.99843,30,-45.18,-10.51,0.00157,2,29,168.27,-5.96,0.00931,30,27.3,-1.48,0.99069,2,30,92.28,1.15,0.00696,31,16.75,-0.19,0.99304],"hull":18,"edges":[8,38,8,10,12,38,10,12,12,14,22,36,36,26,24,22,36,24,24,26,26,28,28,30,30,32,32,34,22,20,20,38,38,18,14,16,18,16,18,20,34,0,2,36,0,2,2,4,36,4,36,6,4,6,6,8],"width":107,"height":169}},"youjiao":{"youjiao":{"type":"mesh","uvs":[0.04011,0.37013,0.03588,0.21783,0.14495,0.14328,0.32904,0.11521,0.60442,0.24235,0.58464,0.32986,0.58464,0.39591,0.67745,0.48507,0.93914,0.56598,1,0.66009,1,0.79358,0.93105,1,0.06362,1,0,0.76698,0,0.65413,0.28733,0.49206],"triangles":[15,6,7,8,9,10,10,11,7,10,7,8,12,15,7,11,12,7,5,3,4,0,1,2,5,15,3,15,2,3,6,15,5,0,2,15,14,0,15,13,14,15,12,13,15],"vertices":[2,37,69.27,-39.77,0.9899,35,-40.84,3.28,0.0101,1,37,50.15,-44.35,1,2,37,37.63,-31.35,0.99999,35,-37.62,35.86,1.0E-5,2,37,28.85,-6.85,0.99993,35,-14.86,48.48,7.0E-5,2,37,37.07,34.23,0.76855,35,27.01,46.99,0.23145,2,37,48.68,33.81,0.63501,35,28.47,35.45,0.36499,2,37,57.02,35.55,0.38605,35,31.53,27.5,0.61395,2,37,65.65,50.61,0.05034,35,47.78,21.42,0.94966,1,35,85.72,24.81,1,1,35,98.03,16.53,1,1,35,104.2,0.45,1,1,35,104.73,-27.87,1,2,37,148.15,-20.03,0.14357,35,-8.64,-71.39,0.85643,2,37,120.53,-34.86,0.35887,35,-27.73,-46.52,0.64113,2,37,106.28,-37.82,0.54966,35,-32.95,-32.93,0.45034,1,37,77.63,-2.69,1],"hull":15,"edges":[4,6,6,8,8,10,10,12,12,14,14,16,16,18,4,2,2,0,0,28,26,28,26,24,18,20,22,24,20,22,10,30,30,14,12,30],"width":140,"height":129}},"youjiao2":{"youjiao":{"type":"mesh","uvs":[0.01496,0.58581,0.03661,0.45719,0.05757,0.21831,0.2027,0.1185,0.36444,0.12367,0.56107,0.19078,0.60843,0.29903,0.5912,0.3818,0.66731,0.45925,0.94322,0.55734,1,0.65715,1,1,0.08054,1,0,0.78509,0,0.67463,0.24882,0.51792],"triangles":[15,7,8,12,13,15,8,9,10,11,8,10,12,15,8,11,12,8,5,6,4,15,3,4,2,3,15,1,2,15,15,6,7,4,6,15,0,1,15,15,13,14,0,15,14],"vertices":[2,40,102.47,-30.87,0.72646,38,-27.84,-18.94,0.27354,2,40,85.61,-30.86,0.96983,38,-30.95,-2.37,0.03017,1,40,54.76,-33.48,1,1,40,38.46,-15.79,1,2,40,35.07,6.61,0.98308,38,-3.53,54.25,0.01692,2,40,38.66,35.24,0.7569,38,25.27,56.03,0.2431,2,40,51.22,44.26,0.60611,38,36.47,45.37,0.39389,2,40,62.16,43.8,0.39597,38,38.04,34.54,0.60403,2,40,70.08,56.07,0.10321,38,51.57,29.03,0.89679,1,38,92.17,31.06,1,1,38,104.2,21.89,1,1,38,120.06,-19.4,1,2,40,153.4,-12.28,0.13011,38,-0.12,-65.53,0.86989,2,40,128.14,-28.33,0.33912,38,-20.58,-43.69,0.66088,2,40,114.12,-30.88,0.52208,38,-25.69,-30.39,0.47792,2,40,88,-0.22,0.78582,38,-0.41,0.97,0.21418],"hull":15,"edges":[6,8,8,10,30,12,10,12,12,14,14,16,16,30,16,18,22,20,18,20,6,4,4,2,26,28,22,24,26,24,14,30,30,2,2,0,0,28,30,0],"width":140,"height":129}},"youshou":{"youshou":{"type":"mesh","uvs":[0.92622,0.06813,1,0.1982,1,0.37729,1,0.5698,1,0.80186,0.91487,1,0.68563,1,0.37696,0.8583,0.26348,0.87761,0.15226,0.6875,0.07385,0.51693,0,0.35628,0,0.15428,0.08644,0.07407,0.29525,0,0.48381,0,0.75599,0,0.57844,0.42868,0.52416,0.20042],"triangles":[2,17,1,17,2,3,9,10,17,7,17,3,7,9,17,3,4,7,8,9,7,6,7,4,5,6,4,18,15,16,18,11,12,14,15,18,13,14,18,1,18,0,18,1,17,0,18,16,18,12,13,17,11,18,10,11,17],"vertices":[2,30,29.94,37.59,0.89208,31,-45.44,36.53,0.10792,2,30,48.22,42.25,0.72824,31,-27.13,41.1,0.27176,2,30,72.44,39.66,0.30061,31,-2.92,38.41,0.69939,2,30,98.48,36.89,0.0102,31,23.1,35.52,0.9898,1,31,54.47,32.04,1,1,31,80.41,21.53,1,1,31,78.16,1.25,1,2,30,131.61,-22.41,0.10266,31,55.97,-23.92,0.89734,2,30,133.15,-32.73,0.15771,31,57.47,-34.25,0.84229,2,30,106.39,-39.83,0.49297,31,30.68,-41.23,0.50703,2,30,82.58,-44.31,0.90171,31,6.85,-45.61,0.09829,2,30,60.16,-48.53,0.99925,31,-15.59,-49.73,7.5E-4,1,30,32.84,-45.62,1,1,30,22.81,-36.81,1,1,30,14.77,-17.26,1,1,30,16.55,-0.58,1,2,30,19.12,23.51,0.96742,31,-56.32,22.49,0.03258,1,31,-0.12,0.35,1,1,30,44.03,0.1,1],"hull":17,"edges":[2,34,34,6,2,4,4,6,34,4,34,22,34,18,22,20,20,18,34,20,32,0,0,2,28,26,22,24,26,24,18,16,16,14,14,12,10,12,6,8,10,8,28,30,30,32],"width":89,"height":136}},"youtui1":{"youtui1":{"type":"mesh","uvs":[1,0.24211,0.84099,0.73725,0.77369,0.94684,0.66012,1,0.3286,1,0.13022,0.94836,0.04168,0.82694,0,0.47747,0,0,0.41224,0,1,0,0.466,0.69686,0.43212,0.88132],"triangles":[9,10,0,7,8,9,11,9,0,7,9,11,1,11,0,6,7,11,12,6,11,2,11,1,3,12,11,5,6,12,4,5,12,2,3,11,4,12,3],"vertices":[1,37,-64.97,45.97,1,1,37,-7.43,42.33,1,1,37,16.93,40.8,1,1,37,26.19,29.34,1,1,37,36.76,-8.67,1,1,37,37.61,-32.93,1,1,37,27.57,-46.66,1,1,37,-8.14,-61.74,1,1,37,-58.74,-75.82,1,1,37,-71.88,-28.55,1,1,37,-90.63,38.83,1,1,37,0.25,-1.85,1,1,37,20.88,-0.3,1],"hull":11,"edges":[14,16,14,22,12,22,14,12,12,10,10,8,6,8,6,4,0,20,16,18,18,20,0,2,2,4,22,2],"width":119,"height":110}},"youtui2":{"youtui2":{"type":"mesh","uvs":[0.91429,0.08966,1,0.23564,1,0.40635,0.94476,0.50895,0.76088,0.82373,0.66071,0.93512,0.53985,1,0.24028,1,0.12189,0.9537,0.05014,0.84643,0,0.48955,0,0.26361,0.15187,0.07967,0.41848,0,0.74118,0,0.54972,0.37446,0.39076,0.95477],"triangles":[7,16,6,6,16,5,7,8,16,4,5,16,16,8,9,15,4,16,16,9,15,9,10,15,4,15,3,10,11,15,11,12,15,3,15,2,15,1,2,12,13,15,15,0,1,15,14,0,15,13,14],"vertices":[1,36,42.32,40.01,1,1,36,62.88,44.87,1,3,36,85.24,40.98,0.96565,37,-5.3,42.57,0.03422,35,28.41,90.15,1.4E-4,3,36,97.77,33.36,0.80857,37,9.18,40.33,0.18739,35,28.53,75.49,0.00403,3,36,135.95,8.61,0.05692,37,53.94,32.08,0.69443,35,27.61,29.99,0.24864,3,36,148.88,-3.5,0.00569,37,70.52,25.84,0.38244,35,24.12,12.62,0.61187,3,36,155.38,-16.53,0,37,81.5,16.29,1.7E-4,35,16.47,0.24,0.99983,2,37,87.86,-12.06,0.37878,35,-10.49,-10.61,0.62122,2,37,84.37,-24.62,0.62116,35,-23.44,-9.18,0.37884,2,37,71.97,-34.53,0.82459,35,-35.23,1.46,0.17541,3,36,79.51,-56.48,0.02775,37,26.72,-49.66,0.97173,35,-57.45,43.68,5.2E-4,2,36,49.91,-51.33,0.28734,37,-2.6,-56.24,0.71266,2,36,28.33,-32.62,0.69626,37,-29.7,-47.21,0.30374,2,36,22.33,-5.33,0.98663,37,-45.7,-24.3,0.01337,1,36,27.69,25.51,1,1,37,0.11,-0.98,1,2,37,78.8,0.86,0.34714,35,0.81,0.42,0.65286],"hull":15,"edges":[22,30,20,22,30,20,30,2,2,4,6,30,4,6,6,8,8,32,32,10,8,10,10,12,20,18,18,32,32,16,16,18,12,14,16,14,26,24,24,22,26,28,28,0,0,2],"width":97,"height":133}},"zuobi1":{"zuobi1":{"type":"mesh","uvs":[0.77748,0.09692,1,0.21692,1,0.53339,0.97153,0.76021,0.89421,0.77973,0.79349,0.80516,0.76472,0.88417,0.68201,0.95369,0.54176,1,0.33768,1,0.25048,1,0.13181,0.90629,0.10125,0.82096,0.09945,0.74986,0,0.6536,0.18954,0.10587,0.30641,0,0.49972,0,0.41092,0.76196,0.16333,0.62539,0.44996,0.58697,0.6413,0.62182,0.79937,0.69345],"triangles":[19,14,15,13,14,19,13,19,18,12,13,18,11,12,18,10,11,18,9,10,18,18,8,9,21,0,1,17,15,16,20,17,0,21,20,0,20,15,17,1,2,21,19,15,20,22,21,2,3,22,2,18,19,20,18,20,21,4,22,3,5,21,22,5,22,4,18,21,5,6,18,5,7,18,6,7,8,18],"vertices":[1,25,-2.98,37.57,1,1,25,13.99,87.78,1,1,25,85.26,104.05,1,1,25,137.63,110.08,1,1,25,145.52,95.78,1,2,25,155.8,77.15,0.98846,26,-3.36,78.8,0.01154,2,25,174.89,75.52,0.93616,26,15.66,76.44,0.06384,2,25,194.28,62.73,0.80337,26,34.55,62.92,0.19663,2,25,211.05,37.35,0.43841,26,50.34,36.93,0.56159,1,26,58.02,-3.79,1,1,26,61.3,-21.18,1,1,26,44.49,-48.86,1,2,25,190.63,-59.03,0.00737,26,26.27,-58.61,0.99263,2,25,174.7,-63.05,0.06573,26,10.2,-62.02,0.93427,2,25,157.52,-87.68,0.20283,26,-7.91,-85.98,0.79717,2,25,25.6,-78.33,0.97447,26,-139.37,-71.62,0.02553,2,25,-3.52,-60.64,0.9962,26,-167.8,-52.83,0.0038,1,25,-12.26,-22.38,1,2,25,163.35,-0.78,0.45381,26,1.23,0.63,0.54619,2,25,143.78,-56.8,0.27735,26,-20.46,-54.6,0.72265,2,25,122.18,-2.05,0.98993,26,-39.96,0.93,0.01007,1,25,121.38,37.61,1,1,25,130.37,72.57,1],"hull":18,"edges":[26,24,24,22,22,20,16,14,14,12,12,10,6,4,32,30,30,28,28,26,32,34,34,0,4,2,0,2,26,36,36,22,36,10,36,16,28,38,38,40,40,42,42,44,6,8,8,10,44,8,16,18,18,20],"width":203,"height":231}},"zuobi2":{"zuobi2":{"type":"mesh","uvs":[0.8586,0.08867,1,0.2323,1,0.27118,1,0.45418,0.96566,0.57427,0.90743,0.77788,0.8717,0.88944,0.7361,0.95489,0.62551,1,0.24038,1,0.07014,0.90387,0,0.83406,0,0.67846,0.04831,0.37087,0.07799,0.2359,0.13299,0.13854,0.25609,0.06673,0.41323,0,0.69622,0,0.47768,0.34364,0.37096,0.85229],"triangles":[8,20,7,6,7,5,9,20,8,9,10,20,10,11,20,5,7,20,19,20,12,5,20,4,19,12,13,20,11,12,4,20,19,13,14,19,14,15,19,15,16,19,16,17,19,4,19,3,19,2,3,19,0,2,19,18,0,19,17,18,0,1,2],"vertices":[2,25,100.35,41.63,0.99991,27,-125.2,104.97,9.0E-5,3,25,123.14,67.73,0.99259,26,-36.35,70.63,1.5E-4,27,-93.19,118.21,0.00726,3,25,130.48,69.29,0.98711,26,-28.95,71.91,0.00214,27,-85.92,116.35,0.01075,3,25,165.03,76.64,0.84428,26,5.85,77.94,0.09188,27,-51.71,107.57,0.06383,3,25,188.75,76.53,0.62454,26,29.55,76.92,0.22482,27,-30.51,96.92,0.15063,3,25,228.97,76.33,0.23251,26,69.73,75.19,0.30614,27,5.42,78.86,0.46135,3,25,251.12,75.67,0.12901,26,91.84,73.7,0.23674,27,24.97,68.43,0.63425,3,25,267.62,58.81,0.06167,26,107.69,56.21,0.14241,27,32.25,45.98,0.79592,3,25,279.52,44.72,0.02383,26,119.04,41.68,0.05238,27,36.65,28.07,0.9238,3,25,291.3,-10.66,2.0E-5,26,128.71,-14.1,0.52812,27,22.58,-26.77,0.47186,3,25,278.36,-39,1.0E-5,26,114.7,-41.93,0.95779,27,-1.61,-46.4,0.0422,3,25,267.33,-51.89,0,26,103.18,-54.39,0.99812,27,-17.23,-53.04,0.00187,2,25,237.95,-58.13,0,26,73.6,-59.51,1,2,25,178.41,-63.54,0.00625,26,13.89,-62.65,0.99375,2,25,152.02,-64.69,0.11169,26,-12.52,-62.8,0.88831,2,25,131.96,-60.69,0.28378,26,-32.42,-58.04,0.71622,2,25,114.64,-45.88,0.57145,26,-49.16,-42.58,0.42855,2,25,97.24,-25.96,0.8878,26,-65.8,-22.02,0.1122,1,25,88.58,14.72,1,1,26,-2.06,-1.36,1,2,26,97.34,-0.06,0.9291,27,-0.26,-1.09,0.0709],"hull":19,"edges":[4,38,10,40,10,12,14,40,12,14,14,16,36,0,4,2,0,2,34,36,34,32,32,30,30,38,24,40,40,20,22,24,20,22,16,18,20,18,28,30,26,38,28,26,26,24,4,6,38,6,6,8,8,10,38,8,38,28],"width":147,"height":193}},"zuoshou":{"zuoshou":{"type":"mesh","uvs":[0.85906,0.06432,1,0.15936,1,0.26512,1,0.39709,1,0.51922,1,0.60741,0.81769,0.63456,0.74972,0.71829,0.77631,0.81107,0.89452,0.888,0.86202,0.95589,0.71426,1,0.45133,1,0.22626,0.94157,0.06394,0.79408,0,0.577,0,0.43198,0.0116,0.28173,0.02444,0.17285,0.10548,0.04848,0.31234,0,0.64628,0,0.40232,0.4467,0.47951,0.19934],"triangles":[22,3,4,6,22,4,5,6,4,7,22,6,13,14,22,7,13,22,12,13,7,10,8,9,8,12,7,11,12,8,10,11,8,23,20,21,0,1,2,2,23,0,19,20,23,18,19,23,23,17,18,22,17,23,16,17,22,23,2,22,0,23,21,3,22,2,15,16,22,14,15,22],"vertices":[2,26,17.97,46.66,0.84114,27,-53.49,74.08,0.15886,2,26,31.13,68.11,0.70993,27,-32.69,88.24,0.29007,2,26,49.36,71.27,0.58612,27,-14.76,83.64,0.41388,2,26,72.12,75.21,0.33822,27,7.61,77.9,0.66178,2,26,93.18,78.86,0.14742,27,28.31,72.59,0.85258,2,26,108.39,81.5,0.09313,27,43.26,68.75,0.90687,2,26,117.24,58.24,0.03532,27,41.79,43.91,0.96468,2,26,133.23,51.76,0.00103,27,53.72,31.44,0.99897,1,27,70.34,30.86,1,1,27,87.31,42.86,1,1,27,97.74,35.68,1,1,27,100.29,14.59,1,2,26,188.63,20.78,0.01012,27,91.54,-19.54,0.98988,2,26,183.71,-10.68,0.10325,27,74.14,-46.21,0.89675,2,26,161.99,-36.52,0.34595,27,43.73,-60.86,0.65405,2,26,126.02,-51.45,0.7982,27,4.8,-59.72,0.2018,2,26,101.01,-55.78,0.9785,27,-19.78,-53.41,0.0215,1,26,74.84,-58.74,1,1,26,55.77,-60.29,1,1,26,32.47,-53.31,1,1,26,19.38,-27.45,1,2,26,11.74,16.65,0.97456,27,-71.48,49.26,0.02544,1,26,94.35,-2.22,1,2,26,49.93,0.58,0.99924,27,-43.24,18.94,7.6E-4],"hull":22,"edges":[42,0,0,2,40,42,40,38,10,12,12,14,14,16,16,18,18,20,20,22,38,36,30,28,28,26,22,24,26,24,34,36,34,44,2,4,44,4,8,10,44,8,4,6,6,8,6,44,44,30,30,32,44,32,32,34],"width":134,"height":175}},"zuoshou2":{"zuoshou2":{"x":14.6,"y":11.53,"rotation":-178.79,"width":45,"height":110}},"zuotui1":{"zuotui1":{"type":"mesh","uvs":[1,0.5791,0.91856,0.90414,0.71117,1,0.53873,1,0.35696,1,0.09131,0.89768,0,0.71022,0,0.4451,0,0,0.51309,0,1,0,0.53149,0.56085,0.52241,0.25407],"triangles":[0,11,12,5,6,11,1,11,0,4,5,11,3,4,11,11,2,3,1,2,11,12,9,10,12,7,8,12,8,9,7,12,11,0,12,10,6,7,11],"vertices":[2,39,67.21,53.95,0.11102,40,-9.35,51.5,0.88898,1,40,30,50.3,1,1,40,45.52,30.34,1,1,40,49.19,11.91,1,2,39,116.87,-16.14,0.02433,40,53.07,-7.52,0.97567,2,39,104.8,-45.1,0.32846,40,46.89,-38.28,0.67154,2,39,82.68,-55.05,0.62006,40,27.15,-52.36,0.37994,2,39,51.39,-55.05,0.94515,40,-3.53,-58.48,0.05485,1,39,-1.13,-55.05,1,2,39,-1.13,0.88,0.99969,40,-65.98,-13.91,3.1E-4,2,39,-1.13,53.95,0.83104,40,-76.36,38.13,0.16896,1,40,-1.47,1,1,2,39,28.85,1.89,0.99493,40,-36.78,-7.05,0.00507],"hull":11,"edges":[14,16,14,22,12,14,22,12,12,10,10,8,4,2,0,20,2,0,16,18,18,20,4,6,6,8],"width":109,"height":118}},"zuotui1b":{"youtui1":{"x":41.79,"y":3.12,"rotation":87.39,"width":119,"height":110}},"zuotui2":{"zuotui2":{"type":"mesh","uvs":[0.85159,0.06603,1,0.23132,1,0.45044,0.92756,0.72544,0.83443,0.92901,0.73149,1,0.3981,1,0.19529,0.93681,0.07834,0.84022,0.06946,0.72266,0.05613,0.56627,0.03534,0.49436,0,0.37212,0,0.24276,0.12563,0.09019,0.32283,0,0.64742,0,0.53145,0.30333],"triangles":[17,15,16,17,16,0,17,0,1,14,15,17,13,14,17,12,13,17,17,1,2,11,12,17,10,11,17,9,10,17,3,17,2,9,17,3,9,7,8,7,9,6,6,9,3,4,6,3,5,6,4],"vertices":[-40.23,25.53,-20.67,45.07,9.36,51.33,48.56,51.94,78.4,48.46,90.27,40.2,97.21,6.91,92.77,-15.14,81.96,-29.58,66.03,-33.82,44.87,-39.62,35.45,-43.75,19.43,-50.77,1.7,-54.46,-21.82,-46.27,-38.28,-29.16,-45.04,3.26,-1.05,0.34],"hull":17,"edges":[30,28,28,26,30,32,32,0,0,2,2,4,4,6,6,8,8,10,24,26,20,18,18,16,16,14,10,12,14,12,28,34,20,22,22,24,34,22,34,26],"width":102,"height":140}},"zuotui2b":{"youtui2":{"x":12.62,"y":4.3,"rotation":103.75,"width":97,"height":133}}}}],"animations":{"Run":{"slots":{"youbi1":{"attachment":[{"name":"youbi1"},{"time":0.2333,"name":"youbi1"},{"time":0.4667,"name":"youbi1"}]},"youbi2":{"attachment":[{"name":"youbi2"},{"time":0.2333,"name":"youbi2"},{"time":0.4667,"name":"youbi2"}]},"youshou":{"attachment":[{"name":"youshou"},{"time":0.2333,"name":"youshou"},{"time":0.4667,"name":"youshou"}]},"zuobi1":{"attachment":[{"name":"zuobi1"},{"time":0.2333,"name":"zuobi1"},{"time":0.4667,"name":"zuobi1"}]},"zuobi2":{"attachment":[{"name":"zuobi2"},{"time":0.2333,"name":"zuobi2"},{"time":0.4667,"name":"zuobi2"}]},"zuoshou":{"attachment":[{"name":"zuoshou"},{"time":0.2333,"name":"zuoshou"},{"time":0.4667,"name":"zuoshou"}]},"zuotui1":{"attachment":[{"name":null},{"time":0.2333,"name":null},{"time":0.4667,"name":null}]},"zuotui1b":{"attachment":[{"name":"youtui1"},{"time":0.2333,"name":"youtui1"},{"time":0.4667,"name":"youtui1"}]},"zuotui2":{"attachment":[{"name":null},{"time":0.2333,"name":null},{"time":0.4667,"name":null}]},"zuotui2b":{"attachment":[{"name":"youtui2"},{"time":0.2333,"name":"youtui2"},{"time":0.4667,"name":"youtui2"}]}},"bones":{"2":{"rotate":[{"angle":-107.05},{"time":0.0667,"angle":-112.71},{"time":0.1667,"angle":-9.98},{"time":0.2333,"angle":67.67},{"time":0.3,"angle":31.93},{"time":0.4,"angle":-57.12},{"time":0.4667,"angle":-107.05}],"translate":[{"x":-180.74,"y":78.46},{"time":0.0667,"x":-147.53,"y":22.31},{"time":0.1333,"x":-81.37,"y":7.7},{"time":0.1667,"x":-39.39,"y":22.15},{"time":0.2333,"x":85.58,"y":100.03},{"time":0.3,"x":29.47,"y":-24.58},{"time":0.3333,"x":-21.43,"y":-29.85},{"time":0.4,"x":-136.06,"y":-3.09},{"time":0.4667,"x":-180.74,"y":78.46}]},"1":{"rotate":[{"angle":72.74},{"time":0.0667,"angle":8.21},{"time":0.1,"angle":-7.74},{"time":0.1667,"angle":-49.58},{"time":0.2333,"angle":-128.09},{"time":0.3333,"angle":-71.66},{"time":0.4667,"angle":72.74}],"translate":[{"x":190.3,"y":69.71},{"time":0.0667,"x":102.61,"y":-7.36},{"time":0.1,"x":108.3,"y":-22.28},{"time":0.1667,"x":-72.03,"y":21.71},{"time":0.2333,"x":-141.49,"y":154.83},{"time":0.3333,"x":-19.86,"y":48.25},{"time":0.4,"x":77.31,"y":57.65},{"time":0.4667,"x":190.3,"y":69.71}]},"root":{"translate":[{"curve":"stepped"},{"time":0.2333,"curve":"stepped"},{"time":0.4667}]},"bone":{"rotate":[{"angle":-5.63,"curve":"stepped"},{"time":0.2333,"angle":-5.63,"curve":"stepped"},{"time":0.4667,"angle":-5.63}],"translate":[{"x":-1.02,"y":-13.76},{"time":0.1,"x":-1.02,"y":-56.17},{"time":0.1667,"x":-1.02,"y":-0.06},{"time":0.2333,"x":-1.02,"y":-13.76},{"time":0.3333,"x":-1.02,"y":-56.17},{"time":0.4,"x":-1.02,"y":-0.06},{"time":0.4667,"x":-1.02,"y":-13.76}]},"shenti":{"rotate":[{"angle":4.24,"curve":"stepped"},{"time":0.2333,"angle":4.24,"curve":"stepped"},{"time":0.4667,"angle":4.24}],"translate":[{"curve":"stepped"},{"time":0.2333,"curve":"stepped"},{"time":0.4667}],"scale":[{"curve":"stepped"},{"time":0.2333,"curve":"stepped"},{"time":0.4667}]},"shenti2":{"rotate":[{"angle":1.56,"curve":"stepped"},{"time":0.2333,"angle":1.56,"curve":"stepped"},{"time":0.4667,"angle":1.56}],"translate":[{"x":9.31,"y":0.86},{"time":0.1,"x":-13.03,"y":-1.2},{"time":0.2333,"x":9.31,"y":0.86},{"time":0.3333,"x":-13.03,"y":-1.2},{"time":0.4667,"x":9.31,"y":0.86}]},"tou":{"rotate":[{"angle":3.22,"curve":"stepped"},{"time":0.2333,"angle":3.22,"curve":"stepped"},{"time":0.4667,"angle":3.22}],"translate":[{"curve":"stepped"},{"time":0.2333,"curve":"stepped"},{"time":0.4667}]},"idle":{"rotate":[{"curve":"stepped"},{"time":0.2333,"curve":"stepped"},{"time":0.4667}],"translate":[{"curve":"stepped"},{"time":0.2333,"curve":"stepped"},{"time":0.4667}]},"weijin":{"rotate":[{"angle":-353.66,"curve":"stepped"},{"time":0.2333,"angle":-353.66,"curve":"stepped"},{"time":0.4667,"angle":-353.66}],"translate":[{"curve":"stepped"},{"time":0.2333,"curve":"stepped"},{"time":0.4667}]},"weijin2":{"rotate":[{"angle":-26.53,"curve":0.25,"c3":0.75},{"time":0.2333,"angle":9.8,"curve":0.25,"c3":0.75},{"time":0.4667,"angle":-26.53}],"translate":[{"curve":"stepped"},{"time":0.2333,"curve":"stepped"},{"time":0.4667}]},"weijin3":{"rotate":[{"angle":-34.5,"curve":0.25,"c3":0.75},{"time":0.2333,"angle":1.83,"curve":0.25,"c3":0.75},{"time":0.4667,"angle":-34.5}],"translate":[{"curve":"stepped"},{"time":0.2333,"curve":"stepped"},{"time":0.4667}]},"weijin4":{"rotate":[{"angle":-41.75,"curve":0.25,"c3":0.75},{"time":0.2333,"angle":-5.43,"curve":0.25,"c3":0.75},{"time":0.4667,"angle":-41.75}],"translate":[{"curve":"stepped"},{"time":0.2333,"curve":"stepped"},{"time":0.4667}]},"huzi1":{"rotate":[{"curve":"stepped"},{"time":0.2333,"curve":"stepped"},{"time":0.4667}],"translate":[{"curve":"stepped"},{"time":0.2333,"curve":"stepped"},{"time":0.4667}]},"huzi2":{"rotate":[{"angle":0.13,"curve":"stepped"},{"time":0.2333,"angle":0.13,"curve":"stepped"},{"time":0.4667,"angle":0.13}],"translate":[{"curve":"stepped"},{"time":0.2333,"curve":"stepped"},{"time":0.4667}]},"huzi3":{"rotate":[{"angle":0.13,"curve":"stepped"},{"time":0.2333,"angle":0.13,"curve":"stepped"},{"time":0.4667,"angle":0.13}],"translate":[{"curve":"stepped"},{"time":0.2333,"curve":"stepped"},{"time":0.4667}]},"huzi4":{"rotate":[{"angle":-2.31,"curve":"stepped"},{"time":0.2333,"angle":-2.31,"curve":"stepped"},{"time":0.4667,"angle":-2.31}],"translate":[{"curve":"stepped"},{"time":0.2333,"curve":"stepped"},{"time":0.4667}]},"huzi5":{"rotate":[{"angle":-2.31,"curve":"stepped"},{"time":0.2333,"angle":-2.31,"curve":"stepped"},{"time":0.4667,"angle":-2.31}],"translate":[{"curve":"stepped"},{"time":0.2333,"curve":"stepped"},{"time":0.4667}]},"huzi6":{"rotate":[{"angle":-9.25,"curve":"stepped"},{"time":0.2333,"angle":-9.25,"curve":"stepped"},{"time":0.4667,"angle":-9.25}],"translate":[{"curve":"stepped"},{"time":0.2333,"curve":"stepped"},{"time":0.4667}]},"huzi7":{"rotate":[{"angle":-9.25,"curve":"stepped"},{"time":0.2333,"angle":-9.25,"curve":"stepped"},{"time":0.4667,"angle":-9.25}],"translate":[{"curve":"stepped"},{"time":0.2333,"curve":"stepped"},{"time":0.4667}]},"huzi8":{"rotate":[{"curve":"stepped"},{"time":0.2333,"curve":"stepped"},{"time":0.4667}],"translate":[{"curve":"stepped"},{"time":0.2333,"curve":"stepped"},{"time":0.4667}]},"huzi9":{"rotate":[{"angle":-1.07,"curve":"stepped"},{"time":0.2333,"angle":-1.07,"curve":"stepped"},{"time":0.4667,"angle":-1.07}],"translate":[{"curve":"stepped"},{"time":0.2333,"curve":"stepped"},{"time":0.4667}]},"huzi10":{"rotate":[{"angle":-1.07,"curve":"stepped"},{"time":0.2333,"angle":-1.07,"curve":"stepped"},{"time":0.4667,"angle":-1.07}],"translate":[{"curve":"stepped"},{"time":0.2333,"curve":"stepped"},{"time":0.4667}]},"huzi11":{"rotate":[{"angle":-6.59,"curve":"stepped"},{"time":0.2333,"angle":-6.59,"curve":"stepped"},{"time":0.4667,"angle":-6.59}],"translate":[{"curve":"stepped"},{"time":0.2333,"curve":"stepped"},{"time":0.4667}]},"huzi12":{"rotate":[{"angle":-11.16,"curve":"stepped"},{"time":0.2333,"angle":-11.16,"curve":"stepped"},{"time":0.4667,"angle":-11.16}],"translate":[{"curve":"stepped"},{"time":0.2333,"curve":"stepped"},{"time":0.4667}]},"huzi13":{"rotate":[{"angle":-11.16,"curve":"stepped"},{"time":0.2333,"angle":-11.16,"curve":"stepped"},{"time":0.4667,"angle":-11.16}],"translate":[{"curve":"stepped"},{"time":0.2333,"curve":"stepped"},{"time":0.4667}]},"huzi14":{"rotate":[{"angle":-11.16,"curve":"stepped"},{"time":0.2333,"angle":-11.16,"curve":"stepped"},{"time":0.4667,"angle":-11.16}],"translate":[{"curve":"stepped"},{"time":0.2333,"curve":"stepped"},{"time":0.4667}]},"zuobi1":{"rotate":[{"angle":-48.23,"curve":0.25,"c3":0.75},{"time":0.2333,"angle":60.22,"curve":0.25,"c3":0.75},{"time":0.4667,"angle":-48.23}],"translate":[{"x":5.56,"y":10.64,"curve":0.25,"c3":0.75},{"time":0.2333,"x":-9.85,"y":16.25,"curve":0.25,"c3":0.75},{"time":0.4667,"x":5.56,"y":10.64}]},"zuobi3":{"rotate":[{"angle":26.71,"curve":"stepped"},{"time":0.2333,"angle":26.71,"curve":"stepped"},{"time":0.4667,"angle":26.71}],"translate":[{"x":16.88,"y":-2.62,"curve":"stepped"},{"time":0.2333,"x":16.88,"y":-2.62,"curve":"stepped"},{"time":0.4667,"x":16.88,"y":-2.62}]},"zuoshou":{"rotate":[{"angle":13.77,"curve":0.25,"c3":0.75},{"time":0.2333,"angle":-4.16,"curve":0.25,"c3":0.75},{"time":0.4667,"angle":13.77}],"translate":[{"x":-1.46,"y":-1.25,"curve":0.25,"c3":0.75},{"time":0.2333,"x":-9.88,"y":-12.89,"curve":0.25,"c3":0.75},{"time":0.4667,"x":-1.46,"y":-1.25}]},"weapon":{"rotate":[{"angle":20.53,"curve":"stepped"},{"time":0.2333,"angle":20.53,"curve":"stepped"},{"time":0.4667,"angle":20.53}],"translate":[{"x":14.77,"y":-13.59,"curve":"stepped"},{"time":0.2333,"x":14.77,"y":-13.59,"curve":"stepped"},{"time":0.4667,"x":14.77,"y":-13.59}]},"shenti3":{"rotate":[{"angle":61.71,"curve":0.25,"c3":0.75},{"time":0.2333,"angle":-76.99,"curve":0.25,"c3":0.75},{"time":0.4667,"angle":61.71}],"translate":[{"x":-3.97,"y":-7.6,"curve":0.25,"c3":0.75},{"time":0.2333,"x":12.84,"y":32,"curve":0.25,"c3":0.75},{"time":0.4667,"x":-3.97,"y":-7.6}]},"youbi2":{"rotate":[{"angle":35.6,"curve":0,"c3":0.75},{"time":0.2333,"angle":81.76,"curve":0,"c3":0.75},{"time":0.4667,"angle":35.6}],"translate":[{"curve":"stepped"},{"time":0.2333,"curve":"stepped"},{"time":0.4667}]},"youshou":{"rotate":[{"angle":25.18,"curve":0,"c3":0.75},{"time":0.2333,"angle":53.4,"curve":0,"c3":0.75},{"time":0.4667,"angle":25.18}],"translate":[{"curve":"stepped"},{"time":0.2333,"curve":"stepped"},{"time":0.4667}]},"kuzi":{"rotate":[{"curve":"stepped"},{"time":0.2333,"curve":"stepped"},{"time":0.4667}],"translate":[{"curve":"stepped"},{"time":0.2333,"curve":"stepped"},{"time":0.4667}]},"kuzi2":{"rotate":[{"angle":-36.67,"curve":0.25,"c3":0.75},{"time":0.2333,"angle":40.13,"curve":0.25,"c3":0.75},{"time":0.4667,"angle":-36.67}],"translate":[{"x":-2.56,"y":-9.83,"curve":0.25,"c3":0.75},{"time":0.2333,"x":-9.25,"y":10.72,"curve":0.25,"c3":0.75},{"time":0.4667,"x":-2.56,"y":-9.83}]},"kuzi3":{"rotate":[{"angle":26.49,"curve":0.25,"c3":0.75},{"time":0.2333,"angle":1.67,"curve":0.25,"c3":0.75},{"time":0.4667,"angle":26.49}],"translate":[{"x":-1.6,"y":43.77,"curve":0.25,"c3":0.75},{"time":0.2333,"x":-2.99,"y":0.64,"curve":0.25,"c3":0.75},{"time":0.4667,"x":-1.6,"y":43.77}]},"youtui1":{"rotate":[{"angle":24.53,"curve":"stepped"},{"time":0.2333,"angle":24.53,"curve":"stepped"},{"time":0.4667,"angle":24.53}],"translate":[{"x":-5.38,"y":-39.51,"curve":"stepped"},{"time":0.2333,"x":-5.38,"y":-39.51,"curve":"stepped"},{"time":0.4667,"x":-5.38,"y":-39.51}]},"youtui3":{"rotate":[{"angle":14.03,"curve":"stepped"},{"time":0.2333,"angle":14.03,"curve":"stepped"},{"time":0.4667,"angle":14.03}],"translate":[{"x":1.69,"y":-1.99,"curve":"stepped"},{"time":0.2333,"x":1.69,"y":-1.99,"curve":"stepped"},{"time":0.4667,"x":1.69,"y":-1.99}]},"zuotui1":{"rotate":[{"angle":-26.65,"curve":"stepped"},{"time":0.2333,"angle":-26.65,"curve":"stepped"},{"time":0.4667,"angle":-26.65}],"translate":[{"x":8.55,"y":60.81},{"time":0.2333,"x":-2.05,"y":-15.33},{"time":0.4667,"x":8.55,"y":60.81}]},"zuotui3":{"rotate":[{"angle":-53.53,"curve":"stepped"},{"time":0.2333,"angle":-53.53,"curve":"stepped"},{"time":0.4667,"angle":-53.53}],"translate":[{"x":-5.64,"y":-5.74,"curve":"stepped"},{"time":0.2333,"x":-5.64,"y":-5.74,"curve":"stepped"},{"time":0.4667,"x":-5.64,"y":-5.74}]},"sheng1":{"rotate":[{"angle":-1.06,"curve":"stepped"},{"time":0.2333,"angle":-1.06,"curve":"stepped"},{"time":0.4667,"angle":-1.06}],"translate":[{"curve":"stepped"},{"time":0.2333,"curve":"stepped"},{"time":0.4667}]},"sheng2":{"rotate":[{"angle":-12.64,"curve":"stepped"},{"time":0.2333,"angle":-12.64,"curve":"stepped"},{"time":0.4667,"angle":-12.64}],"translate":[{"curve":"stepped"},{"time":0.2333,"curve":"stepped"},{"time":0.4667}]},"sheng3":{"rotate":[{"angle":-19.72,"curve":0.25,"c3":0.75},{"time":0.2333,"angle":8.53,"curve":0.25,"c3":0.75},{"time":0.4667,"angle":-19.72}],"translate":[{"curve":"stepped"},{"time":0.2333,"curve":"stepped"},{"time":0.4667}]},"sheng4":{"rotate":[{"angle":-26.39,"curve":0.25,"c3":0.75},{"time":0.2333,"angle":-5.36,"curve":0.25,"c3":0.75},{"time":0.4667,"angle":-26.39}],"translate":[{"curve":"stepped"},{"time":0.2333,"curve":"stepped"},{"time":0.4667}]},"sheng5":{"rotate":[{"angle":-33.27,"curve":0.25,"c3":0.75},{"time":0.2333,"angle":11.68,"curve":0.25,"c3":0.75},{"time":0.4667,"angle":-33.27}],"translate":[{"curve":"stepped"},{"time":0.2333,"curve":"stepped"},{"time":0.4667}]},"weiba":{"rotate":[{"angle":6.29,"curve":"stepped"},{"time":0.2333,"angle":6.29,"curve":"stepped"},{"time":0.4667,"angle":6.29}],"translate":[{"curve":"stepped"},{"time":0.2333,"curve":"stepped"},{"time":0.4667}]},"weiba2":{"rotate":[{"angle":7.84,"curve":0.25,"c3":0.75},{"time":0.2333,"angle":-5.34,"curve":0.25,"c3":0.75},{"time":0.4667,"angle":7.84}],"translate":[{"curve":"stepped"},{"time":0.2333,"curve":"stepped"},{"time":0.4667}]},"weiba3":{"rotate":[{"angle":1.98,"curve":0.25,"c3":0.75},{"time":0.2333,"angle":-11.2,"curve":0.25,"c3":0.75},{"time":0.4667,"angle":1.98}],"translate":[{"curve":"stepped"},{"time":0.2333,"curve":"stepped"},{"time":0.4667}]},"weiba4":{"rotate":[{"angle":8.12,"curve":0.25,"c3":0.75},{"time":0.2333,"angle":-17.24,"curve":0.25,"c3":0.75},{"time":0.4667,"angle":8.12}],"translate":[{"curve":"stepped"},{"time":0.2333,"curve":"stepped"},{"time":0.4667}]},"weiba5":{"rotate":[{"angle":4.14,"curve":0.25,"c3":0.75},{"time":0.2333,"angle":-21.22,"curve":0.25,"c3":0.75},{"time":0.4667,"angle":4.14}],"translate":[{"curve":"stepped"},{"time":0.2333,"curve":"stepped"},{"time":0.4667}]},"zuoshou3":{"rotate":[{"angle":1.65,"curve":"stepped"},{"time":0.2333,"angle":1.65,"curve":"stepped"},{"time":0.4667,"angle":1.65}],"translate":[{"x":7.8,"y":-11.62,"curve":"stepped"},{"time":0.2333,"x":7.8,"y":-11.62,"curve":"stepped"},{"time":0.4667,"x":7.8,"y":-11.62}]},"tou2":{"rotate":[{"angle":-26.84,"curve":"stepped"},{"time":0.2333,"angle":-26.84,"curve":"stepped"},{"time":0.4667,"angle":-26.84}]}},"ik":{"1":[{"bendPositive":false,"curve":"stepped"},{"time":0.2333,"bendPositive":false,"curve":"stepped"},{"time":0.4667,"bendPositive":false}],"2":[{"bendPositive":false,"curve":"stepped"},{"time":0.2333,"bendPositive":false,"curve":"stepped"},{"time":0.4667,"bendPositive":false}]},"deform":{"default":{"idle":{"idle":[{"offset":6,"vertices":[11.73755,-1.0101,12.40863,-0.44559,0,0,0,0,0,0,0,0,0,0,0,0,0,0,0,0,-6.90082,-0.65038,-7.46509,0.02057]},{"time":0.2333,"offset":4,"vertices":[-15.44177,1.32973,-15.44177,1.32973,-15.44177,1.32973,-15.44177,1.32973]},{"time":0.4667,"offset":6,"vertices":[11.73755,-1.0101,12.40863,-0.44559,0,0,0,0,0,0,0,0,0,0,0,0,0,0,0,0,-6.90082,-0.65038,-7.46509,0.02057]}]},"shenti":{"shenti":[{},{"time":0.1,"offset":42,"vertices":[0.76518,-8.30256,-1.83481,-8.13326,0.76518,-8.30256,-1.83481,-8.13326,23.80045,-6.17908,20.73083,-13.22433,0.76518,-8.30256,-1.83481,-8.13326,23.80045,-6.17908,20.73083,-13.22433,23.80045,-6.17908,20.73083,-13.22433,23.80045,-6.17908,20.73083,-13.22433]},{"time":0.1667,"offset":42,"vertices":[1.24326,-13.49165,-2.98135,-13.21674,1.24326,-13.49165,-2.98135,-13.21674,-17.18717,-15.18965,-21.03612,-9.14428,1.24326,-13.49165,-2.98135,-13.21674,-17.18717,-15.18965,-21.03612,-9.14428,-17.18717,-15.18965,-21.03612,-9.14428,-17.18717,-15.18965,-21.03612,-9.14428]},{"time":0.2333,"offset":42,"vertices":[2.19968,-23.86975,-5.27524,-23.38319,2.19968,-23.86975,-5.27524,-23.38319,2.19968,-23.86975,-5.27524,-23.38319,2.19968,-23.86975,-5.27524,-23.38319,2.19968,-23.86975,-5.27524,-23.38319,2.19968,-23.86975,-5.27524,-23.38319,2.19968,-23.86975,-5.27524,-23.38319]},{"time":0.3333,"offset":42,"vertices":[-0.9566,10.37825,2.29343,10.16685,-0.9566,10.37825,2.29343,10.16685,22.07866,12.50173,24.85907,5.07578,-0.9566,10.37825,2.29343,10.16685,22.07866,12.50173,24.85907,5.07578,22.07866,12.50173,24.85907,5.07578,22.07866,12.50173,24.85907,5.07578]},{"time":0.4,"offset":50,"vertices":[-18.43043,-1.69801,-18.05476,4.07246,0,0,0,0,-18.43043,-1.69801,-18.05476,4.07246,-18.43043,-1.69801,-18.05476,4.07246,-18.43043,-1.69801,-18.05476,4.07246]},{"time":0.4667}]},"yifu1":{"yifu1":[{"offset":20,"vertices":[-3.54044,56.1856,9.2308,37.21208,-2.70596,38.24428,0,0,0,0,0,0,0,0,0,0,0,0,0,0,0,0,-2.5845,28.04117,-1.83075,19.86257],"curve":0.25,"c3":0.75},{"time":0.2333,"offset":20,"vertices":[4.0415,-43.85398,-9.69159,-42.96025,4.0415,-43.85398,-59.5257,-52.61905,-40.37833,-68.42287,-25.50119,-35.21332,-13.3873,-41.36514,0,0,0,0,-3.87308,-17.16847,1.61502,-17.52561,1.61502,-17.52561],"curve":0.25,"c3":0.75},{"time":0.4667,"offset":20,"vertices":[-3.54044,56.1856,9.2308,37.21208,-2.70596,38.24428,0,0,0,0,0,0,0,0,0,0,0,0,0,0,0,0,-2.5845,28.04117,-1.83075,19.86257]}]},"youbi1":{"youbi1":[{"offset":36,"vertices":[3.64723,-11.22333,-0.97528,-11.76059,-0.43785,-14.37567,-14.21968,-22.50403,-42.05948,-24.4339]}]},"zuobi1":{"zuobi1":[{"offset":44,"vertices":[9.55606,28.66931,22.21603,20.48755,22.15809,30.24475,34.01132,15.77936,13.33695,14.80737]},{"time":0.2333,"vertices":[6.20892,-6.94131,13.57898,-25.3398,-4.81708,-11.12425,0,0,0,0,0,0,0,0,0,0,0,0,0,0,0,0,0,0,0,0,0,0,0,0,0,0,0,0,0,0,0,0,0,0,0,0,0,0,9.55606,28.66931,22.21603,20.48755,22.15809,30.24475,34.01132,15.77936,13.33695,14.80737],"curve":0.25,"c3":0.75},{"time":0.4667,"offset":44,"vertices":[9.55606,28.66931,22.21603,20.48755,22.15809,30.24475,34.01132,15.77936,13.33695,14.80737]}]}}},"drawOrder":[{"offsets":[{"slot":"youjiao2","offset":12},{"slot":"youtui2","offset":-5},{"slot":"youtui1","offset":-5}]},{"time":0.2333,"offsets":[{"slot":"youtui2","offset":-5},{"slot":"youtui1","offset":-5}]},{"time":0.4667,"offsets":[{"slot":"youjiao2","offset":12},{"slot":"youtui2","offset":-5},{"slot":"youtui1","offset":-5}]}]}}}