{
"skeleton": { "hash": "XbO0wtdwhgdcUekBsRQeYyQkaNs", "spine": "3.8.99", "images": "./images/", "audio": "" },
"bones": [
	{ "name": "root", "scaleX": 0.5733, "scaleY": 0.5733 },
	{ "name": "atk4_3", "parent": "root", "x": 345.89, "y": 282.2, "color": "ff0000ff" },
	{
		"name": "atk3_5",
		"parent": "root",
		"length": 191.26,
		"rotation": 1.67,
		"x": 428.32,
		"y": 423.13,
		"color": "f200ffff"
	},
	{
		"name": "atk3_6",
		"parent": "root",
		"length": 191.26,
		"rotation": 1.67,
		"x": 651.53,
		"y": 423.13,
		"color": "f200ffff"
	},
	{
		"name": "atk3_7",
		"parent": "root",
		"length": 191.26,
		"rotation": 1.67,
		"x": 949.57,
		"y": 423.13,
		"color": "f200ffff"
	},
	{
		"name": "atk3_8",
		"parent": "root",
		"length": 191.26,
		"rotation": 1.67,
		"x": 1219.37,
		"y": 423.13,
		"color": "f200ffff"
	},
	{
		"name": "ss3",
		"parent": "root",
		"length": 77.06,
		"rotation": -91.19,
		"x": 711.99,
		"y": 309.49,
		"color": "e9ff01ff"
	},
	{
		"name": "ss4",
		"parent": "root",
		"length": 77.06,
		"rotation": -91.19,
		"x": 1138.01,
		"y": 309.49,
		"color": "e9ff01ff"
	},
	{
		"name": "ss5",
		"parent": "root",
		"length": 77.06,
		"rotation": -91.19,
		"x": 885.35,
		"y": 309.49,
		"color": "e9ff01ff"
	},
	{
		"name": "ss6",
		"parent": "root",
		"length": 77.06,
		"rotation": -91.19,
		"x": 1382.9,
		"y": 309.49,
		"color": "e9ff01ff"
	}
],
"slots": [
	{ "name": "atk3_5", "bone": "atk3_5" },
	{ "name": "atk3_7", "bone": "atk3_6" },
	{ "name": "atk3_11", "bone": "atk3_8" },
	{ "name": "atk3_9", "bone": "atk3_7" },
	{ "name": "atk3_6", "bone": "atk3_5", "blend": "additive" },
	{ "name": "atk3_8", "bone": "atk3_6", "blend": "additive" },
	{ "name": "atk3_12", "bone": "atk3_8", "blend": "additive" },
	{ "name": "atk3_10", "bone": "atk3_7", "blend": "additive" },
	{ "name": "atk4_3", "bone": "atk4_3" },
	{ "name": "atk4_4", "bone": "atk4_3", "blend": "additive" },
	{ "name": "ss3", "bone": "ss3" },
	{ "name": "ss7", "bone": "ss5" },
	{ "name": "ss9", "bone": "ss6" },
	{ "name": "ss5", "bone": "ss4" },
	{ "name": "ss4", "bone": "ss3", "blend": "additive" },
	{ "name": "ss8", "bone": "ss5", "blend": "additive" },
	{ "name": "ss10", "bone": "ss6", "blend": "additive" },
	{ "name": "ss6", "bone": "ss4", "blend": "additive" }
],
"skins": [
	{
		"name": "default",
		"attachments": {
			"atk3_5": {
				"x1": {
					"type": "mesh",
					"uvs": [ 1, 1, 0, 1, 0, 0, 1, 0 ],
					"triangles": [ 1, 2, 3, 1, 3, 0 ],
					"vertices": [ 242.59, -257.2, -257.2, -242.59, -242.59, 257.2, 257.2, 242.59 ],
					"hull": 4,
					"edges": [ 0, 2, 2, 4, 4, 6, 0, 6 ],
					"width": 500,
					"height": 500
				},
				"x3": {
					"type": "mesh",
					"uvs": [ 1, 1, 0, 1, 0, 0, 1, 0 ],
					"triangles": [ 1, 2, 3, 1, 3, 0 ],
					"vertices": [ 242.59, -257.2, -257.2, -242.59, -242.59, 257.2, 257.2, 242.59 ],
					"hull": 4,
					"edges": [ 0, 2, 2, 4, 4, 6, 0, 6 ],
					"width": 500,
					"height": 500
				},
				"x5": {
					"type": "mesh",
					"uvs": [ 1, 1, 0, 1, 0, 0, 1, 0 ],
					"triangles": [ 1, 2, 3, 1, 3, 0 ],
					"vertices": [ 242.59, -257.2, -257.2, -242.59, -242.59, 257.2, 257.2, 242.59 ],
					"hull": 4,
					"edges": [ 0, 2, 2, 4, 4, 6, 0, 6 ],
					"width": 500,
					"height": 500
				},
				"x7": {
					"type": "mesh",
					"uvs": [ 1, 1, 0, 1, 0, 0, 1, 0 ],
					"triangles": [ 1, 2, 3, 1, 3, 0 ],
					"vertices": [ 242.59, -257.2, -257.2, -242.59, -242.59, 257.2, 257.2, 242.59 ],
					"hull": 4,
					"edges": [ 0, 2, 2, 4, 4, 6, 0, 6 ],
					"width": 500,
					"height": 500
				},
				"x9": {
					"type": "mesh",
					"uvs": [ 1, 1, 0, 1, 0, 0, 1, 0 ],
					"triangles": [ 1, 2, 3, 1, 3, 0 ],
					"vertices": [ 242.59, -257.2, -257.2, -242.59, -242.59, 257.2, 257.2, 242.59 ],
					"hull": 4,
					"edges": [ 0, 2, 2, 4, 4, 6, 0, 6 ],
					"width": 500,
					"height": 500
				},
				"x11": {
					"type": "mesh",
					"uvs": [ 1, 1, 0, 1, 0, 0, 1, 0 ],
					"triangles": [ 1, 2, 3, 1, 3, 0 ],
					"vertices": [ 242.59, -257.2, -257.2, -242.59, -242.59, 257.2, 257.2, 242.59 ],
					"hull": 4,
					"edges": [ 0, 2, 2, 4, 4, 6, 0, 6 ],
					"width": 500,
					"height": 500
				},
				"x13": {
					"type": "mesh",
					"uvs": [ 1, 1, 0, 1, 0, 0, 1, 0 ],
					"triangles": [ 1, 2, 3, 1, 3, 0 ],
					"vertices": [ 242.59, -257.2, -257.2, -242.59, -242.59, 257.2, 257.2, 242.59 ],
					"hull": 4,
					"edges": [ 0, 2, 2, 4, 4, 6, 0, 6 ],
					"width": 500,
					"height": 500
				}
			},
			"atk3_6": {
				"x1": {
					"type": "mesh",
					"uvs": [ 1, 1, 0, 1, 0, 0, 1, 0 ],
					"triangles": [ 1, 2, 3, 1, 3, 0 ],
					"vertices": [ 242.59, -257.2, -257.2, -242.59, -242.59, 257.2, 257.2, 242.59 ],
					"hull": 4,
					"edges": [ 0, 2, 2, 4, 4, 6, 0, 6 ],
					"width": 500,
					"height": 500
				},
				"x3": {
					"type": "mesh",
					"uvs": [ 1, 1, 0, 1, 0, 0, 1, 0 ],
					"triangles": [ 1, 2, 3, 1, 3, 0 ],
					"vertices": [ 242.59, -257.2, -257.2, -242.59, -242.59, 257.2, 257.2, 242.59 ],
					"hull": 4,
					"edges": [ 0, 2, 2, 4, 4, 6, 0, 6 ],
					"width": 500,
					"height": 500
				},
				"x5": {
					"type": "mesh",
					"uvs": [ 1, 1, 0, 1, 0, 0, 1, 0 ],
					"triangles": [ 1, 2, 3, 1, 3, 0 ],
					"vertices": [ 242.59, -257.2, -257.2, -242.59, -242.59, 257.2, 257.2, 242.59 ],
					"hull": 4,
					"edges": [ 0, 2, 2, 4, 4, 6, 0, 6 ],
					"width": 500,
					"height": 500
				},
				"x7": {
					"type": "mesh",
					"uvs": [ 1, 1, 0, 1, 0, 0, 1, 0 ],
					"triangles": [ 1, 2, 3, 1, 3, 0 ],
					"vertices": [ 242.59, -257.2, -257.2, -242.59, -242.59, 257.2, 257.2, 242.59 ],
					"hull": 4,
					"edges": [ 0, 2, 2, 4, 4, 6, 0, 6 ],
					"width": 500,
					"height": 500
				},
				"x9": {
					"type": "mesh",
					"uvs": [ 1, 1, 0, 1, 0, 0, 1, 0 ],
					"triangles": [ 1, 2, 3, 1, 3, 0 ],
					"vertices": [ 242.59, -257.2, -257.2, -242.59, -242.59, 257.2, 257.2, 242.59 ],
					"hull": 4,
					"edges": [ 0, 2, 2, 4, 4, 6, 0, 6 ],
					"width": 500,
					"height": 500
				},
				"x11": {
					"type": "mesh",
					"uvs": [ 1, 1, 0, 1, 0, 0, 1, 0 ],
					"triangles": [ 1, 2, 3, 1, 3, 0 ],
					"vertices": [ 242.59, -257.2, -257.2, -242.59, -242.59, 257.2, 257.2, 242.59 ],
					"hull": 4,
					"edges": [ 0, 2, 2, 4, 4, 6, 0, 6 ],
					"width": 500,
					"height": 500
				},
				"x13": {
					"type": "mesh",
					"uvs": [ 1, 1, 0, 1, 0, 0, 1, 0 ],
					"triangles": [ 1, 2, 3, 1, 3, 0 ],
					"vertices": [ 242.59, -257.2, -257.2, -242.59, -242.59, 257.2, 257.2, 242.59 ],
					"hull": 4,
					"edges": [ 0, 2, 2, 4, 4, 6, 0, 6 ],
					"width": 500,
					"height": 500
				}
			},
			"atk3_7": {
				"x1": {
					"type": "mesh",
					"uvs": [ 1, 1, 0, 1, 0, 0, 1, 0 ],
					"triangles": [ 1, 2, 3, 1, 3, 0 ],
					"vertices": [ 242.59, -257.2, -257.2, -242.59, -242.59, 257.2, 257.2, 242.59 ],
					"hull": 4,
					"edges": [ 0, 2, 2, 4, 4, 6, 0, 6 ],
					"width": 500,
					"height": 500
				},
				"x3": {
					"type": "mesh",
					"uvs": [ 1, 1, 0, 1, 0, 0, 1, 0 ],
					"triangles": [ 1, 2, 3, 1, 3, 0 ],
					"vertices": [ 242.59, -257.2, -257.2, -242.59, -242.59, 257.2, 257.2, 242.59 ],
					"hull": 4,
					"edges": [ 0, 2, 2, 4, 4, 6, 0, 6 ],
					"width": 500,
					"height": 500
				},
				"x5": {
					"type": "mesh",
					"uvs": [ 1, 1, 0, 1, 0, 0, 1, 0 ],
					"triangles": [ 1, 2, 3, 1, 3, 0 ],
					"vertices": [ 242.59, -257.2, -257.2, -242.59, -242.59, 257.2, 257.2, 242.59 ],
					"hull": 4,
					"edges": [ 0, 2, 2, 4, 4, 6, 0, 6 ],
					"width": 500,
					"height": 500
				},
				"x7": {
					"type": "mesh",
					"uvs": [ 1, 1, 0, 1, 0, 0, 1, 0 ],
					"triangles": [ 1, 2, 3, 1, 3, 0 ],
					"vertices": [ 242.59, -257.2, -257.2, -242.59, -242.59, 257.2, 257.2, 242.59 ],
					"hull": 4,
					"edges": [ 0, 2, 2, 4, 4, 6, 0, 6 ],
					"width": 500,
					"height": 500
				},
				"x9": {
					"type": "mesh",
					"uvs": [ 1, 1, 0, 1, 0, 0, 1, 0 ],
					"triangles": [ 1, 2, 3, 1, 3, 0 ],
					"vertices": [ 242.59, -257.2, -257.2, -242.59, -242.59, 257.2, 257.2, 242.59 ],
					"hull": 4,
					"edges": [ 0, 2, 2, 4, 4, 6, 0, 6 ],
					"width": 500,
					"height": 500
				},
				"x11": {
					"type": "mesh",
					"uvs": [ 1, 1, 0, 1, 0, 0, 1, 0 ],
					"triangles": [ 1, 2, 3, 1, 3, 0 ],
					"vertices": [ 242.59, -257.2, -257.2, -242.59, -242.59, 257.2, 257.2, 242.59 ],
					"hull": 4,
					"edges": [ 0, 2, 2, 4, 4, 6, 0, 6 ],
					"width": 500,
					"height": 500
				},
				"x13": {
					"type": "mesh",
					"uvs": [ 1, 1, 0, 1, 0, 0, 1, 0 ],
					"triangles": [ 1, 2, 3, 1, 3, 0 ],
					"vertices": [ 242.59, -257.2, -257.2, -242.59, -242.59, 257.2, 257.2, 242.59 ],
					"hull": 4,
					"edges": [ 0, 2, 2, 4, 4, 6, 0, 6 ],
					"width": 500,
					"height": 500
				}
			},
			"atk3_8": {
				"x1": {
					"type": "mesh",
					"uvs": [ 1, 1, 0, 1, 0, 0, 1, 0 ],
					"triangles": [ 1, 2, 3, 1, 3, 0 ],
					"vertices": [ 242.59, -257.2, -257.2, -242.59, -242.59, 257.2, 257.2, 242.59 ],
					"hull": 4,
					"edges": [ 0, 2, 2, 4, 4, 6, 0, 6 ],
					"width": 500,
					"height": 500
				},
				"x3": {
					"type": "mesh",
					"uvs": [ 1, 1, 0, 1, 0, 0, 1, 0 ],
					"triangles": [ 1, 2, 3, 1, 3, 0 ],
					"vertices": [ 242.59, -257.2, -257.2, -242.59, -242.59, 257.2, 257.2, 242.59 ],
					"hull": 4,
					"edges": [ 0, 2, 2, 4, 4, 6, 0, 6 ],
					"width": 500,
					"height": 500
				},
				"x5": {
					"type": "mesh",
					"uvs": [ 1, 1, 0, 1, 0, 0, 1, 0 ],
					"triangles": [ 1, 2, 3, 1, 3, 0 ],
					"vertices": [ 242.59, -257.2, -257.2, -242.59, -242.59, 257.2, 257.2, 242.59 ],
					"hull": 4,
					"edges": [ 0, 2, 2, 4, 4, 6, 0, 6 ],
					"width": 500,
					"height": 500
				},
				"x7": {
					"type": "mesh",
					"uvs": [ 1, 1, 0, 1, 0, 0, 1, 0 ],
					"triangles": [ 1, 2, 3, 1, 3, 0 ],
					"vertices": [ 242.59, -257.2, -257.2, -242.59, -242.59, 257.2, 257.2, 242.59 ],
					"hull": 4,
					"edges": [ 0, 2, 2, 4, 4, 6, 0, 6 ],
					"width": 500,
					"height": 500
				},
				"x9": {
					"type": "mesh",
					"uvs": [ 1, 1, 0, 1, 0, 0, 1, 0 ],
					"triangles": [ 1, 2, 3, 1, 3, 0 ],
					"vertices": [ 242.59, -257.2, -257.2, -242.59, -242.59, 257.2, 257.2, 242.59 ],
					"hull": 4,
					"edges": [ 0, 2, 2, 4, 4, 6, 0, 6 ],
					"width": 500,
					"height": 500
				},
				"x11": {
					"type": "mesh",
					"uvs": [ 1, 1, 0, 1, 0, 0, 1, 0 ],
					"triangles": [ 1, 2, 3, 1, 3, 0 ],
					"vertices": [ 242.59, -257.2, -257.2, -242.59, -242.59, 257.2, 257.2, 242.59 ],
					"hull": 4,
					"edges": [ 0, 2, 2, 4, 4, 6, 0, 6 ],
					"width": 500,
					"height": 500
				},
				"x13": {
					"type": "mesh",
					"uvs": [ 1, 1, 0, 1, 0, 0, 1, 0 ],
					"triangles": [ 1, 2, 3, 1, 3, 0 ],
					"vertices": [ 242.59, -257.2, -257.2, -242.59, -242.59, 257.2, 257.2, 242.59 ],
					"hull": 4,
					"edges": [ 0, 2, 2, 4, 4, 6, 0, 6 ],
					"width": 500,
					"height": 500
				}
			},
			"atk3_9": {
				"x1": {
					"type": "mesh",
					"uvs": [ 1, 1, 0, 1, 0, 0, 1, 0 ],
					"triangles": [ 1, 2, 3, 1, 3, 0 ],
					"vertices": [ 242.59, -257.2, -257.2, -242.59, -242.59, 257.2, 257.2, 242.59 ],
					"hull": 4,
					"edges": [ 0, 2, 2, 4, 4, 6, 0, 6 ],
					"width": 500,
					"height": 500
				},
				"x3": {
					"type": "mesh",
					"uvs": [ 1, 1, 0, 1, 0, 0, 1, 0 ],
					"triangles": [ 1, 2, 3, 1, 3, 0 ],
					"vertices": [ 242.59, -257.2, -257.2, -242.59, -242.59, 257.2, 257.2, 242.59 ],
					"hull": 4,
					"edges": [ 0, 2, 2, 4, 4, 6, 0, 6 ],
					"width": 500,
					"height": 500
				},
				"x5": {
					"type": "mesh",
					"uvs": [ 1, 1, 0, 1, 0, 0, 1, 0 ],
					"triangles": [ 1, 2, 3, 1, 3, 0 ],
					"vertices": [ 242.59, -257.2, -257.2, -242.59, -242.59, 257.2, 257.2, 242.59 ],
					"hull": 4,
					"edges": [ 0, 2, 2, 4, 4, 6, 0, 6 ],
					"width": 500,
					"height": 500
				},
				"x7": {
					"type": "mesh",
					"uvs": [ 1, 1, 0, 1, 0, 0, 1, 0 ],
					"triangles": [ 1, 2, 3, 1, 3, 0 ],
					"vertices": [ 242.59, -257.2, -257.2, -242.59, -242.59, 257.2, 257.2, 242.59 ],
					"hull": 4,
					"edges": [ 0, 2, 2, 4, 4, 6, 0, 6 ],
					"width": 500,
					"height": 500
				},
				"x9": {
					"type": "mesh",
					"uvs": [ 1, 1, 0, 1, 0, 0, 1, 0 ],
					"triangles": [ 1, 2, 3, 1, 3, 0 ],
					"vertices": [ 242.59, -257.2, -257.2, -242.59, -242.59, 257.2, 257.2, 242.59 ],
					"hull": 4,
					"edges": [ 0, 2, 2, 4, 4, 6, 0, 6 ],
					"width": 500,
					"height": 500
				},
				"x11": {
					"type": "mesh",
					"uvs": [ 1, 1, 0, 1, 0, 0, 1, 0 ],
					"triangles": [ 1, 2, 3, 1, 3, 0 ],
					"vertices": [ 242.59, -257.2, -257.2, -242.59, -242.59, 257.2, 257.2, 242.59 ],
					"hull": 4,
					"edges": [ 0, 2, 2, 4, 4, 6, 0, 6 ],
					"width": 500,
					"height": 500
				},
				"x13": {
					"type": "mesh",
					"uvs": [ 1, 1, 0, 1, 0, 0, 1, 0 ],
					"triangles": [ 1, 2, 3, 1, 3, 0 ],
					"vertices": [ 242.59, -257.2, -257.2, -242.59, -242.59, 257.2, 257.2, 242.59 ],
					"hull": 4,
					"edges": [ 0, 2, 2, 4, 4, 6, 0, 6 ],
					"width": 500,
					"height": 500
				}
			},
			"atk3_10": {
				"x1": {
					"type": "mesh",
					"uvs": [ 1, 1, 0, 1, 0, 0, 1, 0 ],
					"triangles": [ 1, 2, 3, 1, 3, 0 ],
					"vertices": [ 242.59, -257.2, -257.2, -242.59, -242.59, 257.2, 257.2, 242.59 ],
					"hull": 4,
					"edges": [ 0, 2, 2, 4, 4, 6, 0, 6 ],
					"width": 500,
					"height": 500
				},
				"x3": {
					"type": "mesh",
					"uvs": [ 1, 1, 0, 1, 0, 0, 1, 0 ],
					"triangles": [ 1, 2, 3, 1, 3, 0 ],
					"vertices": [ 242.59, -257.2, -257.2, -242.59, -242.59, 257.2, 257.2, 242.59 ],
					"hull": 4,
					"edges": [ 0, 2, 2, 4, 4, 6, 0, 6 ],
					"width": 500,
					"height": 500
				},
				"x5": {
					"type": "mesh",
					"uvs": [ 1, 1, 0, 1, 0, 0, 1, 0 ],
					"triangles": [ 1, 2, 3, 1, 3, 0 ],
					"vertices": [ 242.59, -257.2, -257.2, -242.59, -242.59, 257.2, 257.2, 242.59 ],
					"hull": 4,
					"edges": [ 0, 2, 2, 4, 4, 6, 0, 6 ],
					"width": 500,
					"height": 500
				},
				"x7": {
					"type": "mesh",
					"uvs": [ 1, 1, 0, 1, 0, 0, 1, 0 ],
					"triangles": [ 1, 2, 3, 1, 3, 0 ],
					"vertices": [ 242.59, -257.2, -257.2, -242.59, -242.59, 257.2, 257.2, 242.59 ],
					"hull": 4,
					"edges": [ 0, 2, 2, 4, 4, 6, 0, 6 ],
					"width": 500,
					"height": 500
				},
				"x9": {
					"type": "mesh",
					"uvs": [ 1, 1, 0, 1, 0, 0, 1, 0 ],
					"triangles": [ 1, 2, 3, 1, 3, 0 ],
					"vertices": [ 242.59, -257.2, -257.2, -242.59, -242.59, 257.2, 257.2, 242.59 ],
					"hull": 4,
					"edges": [ 0, 2, 2, 4, 4, 6, 0, 6 ],
					"width": 500,
					"height": 500
				},
				"x11": {
					"type": "mesh",
					"uvs": [ 1, 1, 0, 1, 0, 0, 1, 0 ],
					"triangles": [ 1, 2, 3, 1, 3, 0 ],
					"vertices": [ 242.59, -257.2, -257.2, -242.59, -242.59, 257.2, 257.2, 242.59 ],
					"hull": 4,
					"edges": [ 0, 2, 2, 4, 4, 6, 0, 6 ],
					"width": 500,
					"height": 500
				},
				"x13": {
					"type": "mesh",
					"uvs": [ 1, 1, 0, 1, 0, 0, 1, 0 ],
					"triangles": [ 1, 2, 3, 1, 3, 0 ],
					"vertices": [ 242.59, -257.2, -257.2, -242.59, -242.59, 257.2, 257.2, 242.59 ],
					"hull": 4,
					"edges": [ 0, 2, 2, 4, 4, 6, 0, 6 ],
					"width": 500,
					"height": 500
				}
			},
			"atk3_11": {
				"x1": {
					"type": "mesh",
					"uvs": [ 1, 1, 0, 1, 0, 0, 1, 0 ],
					"triangles": [ 1, 2, 3, 1, 3, 0 ],
					"vertices": [ 242.59, -257.2, -257.2, -242.59, -242.59, 257.2, 257.2, 242.59 ],
					"hull": 4,
					"edges": [ 0, 2, 2, 4, 4, 6, 0, 6 ],
					"width": 500,
					"height": 500
				},
				"x2": {
					"type": "mesh",
					"uvs": [ 1, 1, 0, 1, 0, 0, 1, 0 ],
					"triangles": [ 1, 2, 3, 1, 3, 0 ],
					"vertices": [ 242.59, -257.2, -257.2, -242.59, -242.59, 257.2, 257.2, 242.59 ],
					"hull": 4,
					"edges": [ 0, 2, 2, 4, 4, 6, 0, 6 ],
					"width": 500,
					"height": 500
				},
				"x3": {
					"type": "mesh",
					"uvs": [ 1, 1, 0, 1, 0, 0, 1, 0 ],
					"triangles": [ 1, 2, 3, 1, 3, 0 ],
					"vertices": [ 242.59, -257.2, -257.2, -242.59, -242.59, 257.2, 257.2, 242.59 ],
					"hull": 4,
					"edges": [ 0, 2, 2, 4, 4, 6, 0, 6 ],
					"width": 500,
					"height": 500
				},
				"x4": {
					"type": "mesh",
					"uvs": [ 1, 1, 0, 1, 0, 0, 1, 0 ],
					"triangles": [ 1, 2, 3, 1, 3, 0 ],
					"vertices": [ 242.59, -257.2, -257.2, -242.59, -242.59, 257.2, 257.2, 242.59 ],
					"hull": 4,
					"edges": [ 0, 2, 2, 4, 4, 6, 0, 6 ],
					"width": 500,
					"height": 500
				},
				"x5": {
					"type": "mesh",
					"uvs": [ 1, 1, 0, 1, 0, 0, 1, 0 ],
					"triangles": [ 1, 2, 3, 1, 3, 0 ],
					"vertices": [ 242.59, -257.2, -257.2, -242.59, -242.59, 257.2, 257.2, 242.59 ],
					"hull": 4,
					"edges": [ 0, 2, 2, 4, 4, 6, 0, 6 ],
					"width": 500,
					"height": 500
				},
				"x6": {
					"type": "mesh",
					"uvs": [ 1, 1, 0, 1, 0, 0, 1, 0 ],
					"triangles": [ 1, 2, 3, 1, 3, 0 ],
					"vertices": [ 242.59, -257.2, -257.2, -242.59, -242.59, 257.2, 257.2, 242.59 ],
					"hull": 4,
					"edges": [ 0, 2, 2, 4, 4, 6, 0, 6 ],
					"width": 500,
					"height": 500
				},
				"x7": {
					"type": "mesh",
					"uvs": [ 1, 1, 0, 1, 0, 0, 1, 0 ],
					"triangles": [ 1, 2, 3, 1, 3, 0 ],
					"vertices": [ 242.59, -257.2, -257.2, -242.59, -242.59, 257.2, 257.2, 242.59 ],
					"hull": 4,
					"edges": [ 0, 2, 2, 4, 4, 6, 0, 6 ],
					"width": 500,
					"height": 500
				},
				"x8": {
					"type": "mesh",
					"uvs": [ 1, 1, 0, 1, 0, 0, 1, 0 ],
					"triangles": [ 1, 2, 3, 1, 3, 0 ],
					"vertices": [ 242.59, -257.2, -257.2, -242.59, -242.59, 257.2, 257.2, 242.59 ],
					"hull": 4,
					"edges": [ 0, 2, 2, 4, 4, 6, 0, 6 ],
					"width": 500,
					"height": 500
				},
				"x9": {
					"type": "mesh",
					"uvs": [ 1, 1, 0, 1, 0, 0, 1, 0 ],
					"triangles": [ 1, 2, 3, 1, 3, 0 ],
					"vertices": [ 242.59, -257.2, -257.2, -242.59, -242.59, 257.2, 257.2, 242.59 ],
					"hull": 4,
					"edges": [ 0, 2, 2, 4, 4, 6, 0, 6 ],
					"width": 500,
					"height": 500
				},
				"x10": {
					"type": "mesh",
					"uvs": [ 1, 1, 0, 1, 0, 0, 1, 0 ],
					"triangles": [ 1, 2, 3, 1, 3, 0 ],
					"vertices": [ 242.59, -257.2, -257.2, -242.59, -242.59, 257.2, 257.2, 242.59 ],
					"hull": 4,
					"edges": [ 0, 2, 2, 4, 4, 6, 0, 6 ],
					"width": 500,
					"height": 500
				},
				"x11": {
					"type": "mesh",
					"uvs": [ 1, 1, 0, 1, 0, 0, 1, 0 ],
					"triangles": [ 1, 2, 3, 1, 3, 0 ],
					"vertices": [ 242.59, -257.2, -257.2, -242.59, -242.59, 257.2, 257.2, 242.59 ],
					"hull": 4,
					"edges": [ 0, 2, 2, 4, 4, 6, 0, 6 ],
					"width": 500,
					"height": 500
				},
				"x12": {
					"type": "mesh",
					"uvs": [ 1, 1, 0, 1, 0, 0, 1, 0 ],
					"triangles": [ 1, 2, 3, 1, 3, 0 ],
					"vertices": [ 242.59, -257.2, -257.2, -242.59, -242.59, 257.2, 257.2, 242.59 ],
					"hull": 4,
					"edges": [ 0, 2, 2, 4, 4, 6, 0, 6 ],
					"width": 500,
					"height": 500
				},
				"x13": {
					"type": "mesh",
					"uvs": [ 1, 1, 0, 1, 0, 0, 1, 0 ],
					"triangles": [ 1, 2, 3, 1, 3, 0 ],
					"vertices": [ 242.59, -257.2, -257.2, -242.59, -242.59, 257.2, 257.2, 242.59 ],
					"hull": 4,
					"edges": [ 0, 2, 2, 4, 4, 6, 0, 6 ],
					"width": 500,
					"height": 500
				},
				"x14": {
					"type": "mesh",
					"uvs": [ 1, 1, 0, 1, 0, 0, 1, 0 ],
					"triangles": [ 1, 2, 3, 1, 3, 0 ],
					"vertices": [ 242.59, -257.2, -257.2, -242.59, -242.59, 257.2, 257.2, 242.59 ],
					"hull": 4,
					"edges": [ 0, 2, 2, 4, 4, 6, 0, 6 ],
					"width": 500,
					"height": 500
				}
			},
			"atk3_12": {
				"x1": {
					"type": "mesh",
					"uvs": [ 1, 1, 0, 1, 0, 0, 1, 0 ],
					"triangles": [ 1, 2, 3, 1, 3, 0 ],
					"vertices": [ 242.59, -257.2, -257.2, -242.59, -242.59, 257.2, 257.2, 242.59 ],
					"hull": 4,
					"edges": [ 0, 2, 2, 4, 4, 6, 0, 6 ],
					"width": 500,
					"height": 500
				},
				"x2": {
					"type": "mesh",
					"uvs": [ 1, 1, 0, 1, 0, 0, 1, 0 ],
					"triangles": [ 1, 2, 3, 1, 3, 0 ],
					"vertices": [ 242.59, -257.2, -257.2, -242.59, -242.59, 257.2, 257.2, 242.59 ],
					"hull": 4,
					"edges": [ 0, 2, 2, 4, 4, 6, 0, 6 ],
					"width": 500,
					"height": 500
				},
				"x3": {
					"type": "mesh",
					"uvs": [ 1, 1, 0, 1, 0, 0, 1, 0 ],
					"triangles": [ 1, 2, 3, 1, 3, 0 ],
					"vertices": [ 242.59, -257.2, -257.2, -242.59, -242.59, 257.2, 257.2, 242.59 ],
					"hull": 4,
					"edges": [ 0, 2, 2, 4, 4, 6, 0, 6 ],
					"width": 500,
					"height": 500
				},
				"x4": {
					"type": "mesh",
					"uvs": [ 1, 1, 0, 1, 0, 0, 1, 0 ],
					"triangles": [ 1, 2, 3, 1, 3, 0 ],
					"vertices": [ 242.59, -257.2, -257.2, -242.59, -242.59, 257.2, 257.2, 242.59 ],
					"hull": 4,
					"edges": [ 0, 2, 2, 4, 4, 6, 0, 6 ],
					"width": 500,
					"height": 500
				},
				"x5": {
					"type": "mesh",
					"uvs": [ 1, 1, 0, 1, 0, 0, 1, 0 ],
					"triangles": [ 1, 2, 3, 1, 3, 0 ],
					"vertices": [ 242.59, -257.2, -257.2, -242.59, -242.59, 257.2, 257.2, 242.59 ],
					"hull": 4,
					"edges": [ 0, 2, 2, 4, 4, 6, 0, 6 ],
					"width": 500,
					"height": 500
				},
				"x6": {
					"type": "mesh",
					"uvs": [ 1, 1, 0, 1, 0, 0, 1, 0 ],
					"triangles": [ 1, 2, 3, 1, 3, 0 ],
					"vertices": [ 242.59, -257.2, -257.2, -242.59, -242.59, 257.2, 257.2, 242.59 ],
					"hull": 4,
					"edges": [ 0, 2, 2, 4, 4, 6, 0, 6 ],
					"width": 500,
					"height": 500
				},
				"x7": {
					"type": "mesh",
					"uvs": [ 1, 1, 0, 1, 0, 0, 1, 0 ],
					"triangles": [ 1, 2, 3, 1, 3, 0 ],
					"vertices": [ 242.59, -257.2, -257.2, -242.59, -242.59, 257.2, 257.2, 242.59 ],
					"hull": 4,
					"edges": [ 0, 2, 2, 4, 4, 6, 0, 6 ],
					"width": 500,
					"height": 500
				},
				"x8": {
					"type": "mesh",
					"uvs": [ 1, 1, 0, 1, 0, 0, 1, 0 ],
					"triangles": [ 1, 2, 3, 1, 3, 0 ],
					"vertices": [ 242.59, -257.2, -257.2, -242.59, -242.59, 257.2, 257.2, 242.59 ],
					"hull": 4,
					"edges": [ 0, 2, 2, 4, 4, 6, 0, 6 ],
					"width": 500,
					"height": 500
				},
				"x9": {
					"type": "mesh",
					"uvs": [ 1, 1, 0, 1, 0, 0, 1, 0 ],
					"triangles": [ 1, 2, 3, 1, 3, 0 ],
					"vertices": [ 242.59, -257.2, -257.2, -242.59, -242.59, 257.2, 257.2, 242.59 ],
					"hull": 4,
					"edges": [ 0, 2, 2, 4, 4, 6, 0, 6 ],
					"width": 500,
					"height": 500
				},
				"x10": {
					"type": "mesh",
					"uvs": [ 1, 1, 0, 1, 0, 0, 1, 0 ],
					"triangles": [ 1, 2, 3, 1, 3, 0 ],
					"vertices": [ 242.59, -257.2, -257.2, -242.59, -242.59, 257.2, 257.2, 242.59 ],
					"hull": 4,
					"edges": [ 0, 2, 2, 4, 4, 6, 0, 6 ],
					"width": 500,
					"height": 500
				},
				"x11": {
					"type": "mesh",
					"uvs": [ 1, 1, 0, 1, 0, 0, 1, 0 ],
					"triangles": [ 1, 2, 3, 1, 3, 0 ],
					"vertices": [ 242.59, -257.2, -257.2, -242.59, -242.59, 257.2, 257.2, 242.59 ],
					"hull": 4,
					"edges": [ 0, 2, 2, 4, 4, 6, 0, 6 ],
					"width": 500,
					"height": 500
				},
				"x12": {
					"type": "mesh",
					"uvs": [ 1, 1, 0, 1, 0, 0, 1, 0 ],
					"triangles": [ 1, 2, 3, 1, 3, 0 ],
					"vertices": [ 242.59, -257.2, -257.2, -242.59, -242.59, 257.2, 257.2, 242.59 ],
					"hull": 4,
					"edges": [ 0, 2, 2, 4, 4, 6, 0, 6 ],
					"width": 500,
					"height": 500
				},
				"x13": {
					"type": "mesh",
					"uvs": [ 1, 1, 0, 1, 0, 0, 1, 0 ],
					"triangles": [ 1, 2, 3, 1, 3, 0 ],
					"vertices": [ 242.59, -257.2, -257.2, -242.59, -242.59, 257.2, 257.2, 242.59 ],
					"hull": 4,
					"edges": [ 0, 2, 2, 4, 4, 6, 0, 6 ],
					"width": 500,
					"height": 500
				},
				"x14": {
					"type": "mesh",
					"uvs": [ 1, 1, 0, 1, 0, 0, 1, 0 ],
					"triangles": [ 1, 2, 3, 1, 3, 0 ],
					"vertices": [ 242.59, -257.2, -257.2, -242.59, -242.59, 257.2, 257.2, 242.59 ],
					"hull": 4,
					"edges": [ 0, 2, 2, 4, 4, 6, 0, 6 ],
					"width": 500,
					"height": 500
				}
			},
			"atk4_3": {
				"atk4_1": {
					"type": "mesh",
					"uvs": [ 1, 1, 0, 1, 0, 0, 1, 0 ],
					"triangles": [ 1, 2, 3, 1, 3, 0 ],
					"vertices": [ 100, -250, -100, -250, -100, 250, 100, 250 ],
					"hull": 4,
					"edges": [ 0, 2, 2, 4, 4, 6, 0, 6 ],
					"width": 200,
					"height": 500
				},
				"atk4_3": {
					"type": "mesh",
					"uvs": [ 1, 1, 0, 1, 0, 0, 1, 0 ],
					"triangles": [ 1, 2, 3, 1, 3, 0 ],
					"vertices": [ 100, -250, -100, -250, -100, 250, 100, 250 ],
					"hull": 4,
					"edges": [ 0, 2, 2, 4, 4, 6, 0, 6 ],
					"width": 200,
					"height": 500
				},
				"atk4_5": {
					"type": "mesh",
					"uvs": [ 1, 1, 0, 1, 0, 0, 1, 0 ],
					"triangles": [ 1, 2, 3, 1, 3, 0 ],
					"vertices": [ 100, -250, -100, -250, -100, 250, 100, 250 ],
					"hull": 4,
					"edges": [ 0, 2, 2, 4, 4, 6, 0, 6 ],
					"width": 200,
					"height": 500
				},
				"atk4_7": {
					"type": "mesh",
					"uvs": [ 1, 1, 0, 1, 0, 0, 1, 0 ],
					"triangles": [ 1, 2, 3, 1, 3, 0 ],
					"vertices": [ 100, -250, -100, -250, -100, 250, 100, 250 ],
					"hull": 4,
					"edges": [ 0, 2, 2, 4, 4, 6, 0, 6 ],
					"width": 200,
					"height": 500
				},
				"atk4_9": {
					"type": "mesh",
					"uvs": [ 1, 1, 0, 1, 0, 0, 1, 0 ],
					"triangles": [ 1, 2, 3, 1, 3, 0 ],
					"vertices": [ 100, -250, -100, -250, -100, 250, 100, 250 ],
					"hull": 4,
					"edges": [ 0, 2, 2, 4, 4, 6, 0, 6 ],
					"width": 200,
					"height": 500
				},
				"atk4_11": {
					"type": "mesh",
					"uvs": [ 1, 1, 0, 1, 0, 0, 1, 0 ],
					"triangles": [ 1, 2, 3, 1, 3, 0 ],
					"vertices": [ 100, -250, -100, -250, -100, 250, 100, 250 ],
					"hull": 4,
					"edges": [ 0, 2, 2, 4, 4, 6, 0, 6 ],
					"width": 200,
					"height": 500
				}
			},
			"atk4_4": {
				"atk4_1": {
					"type": "mesh",
					"uvs": [ 1, 1, 0, 1, 0, 0, 1, 0 ],
					"triangles": [ 1, 2, 3, 1, 3, 0 ],
					"vertices": [ 100, -250, -100, -250, -100, 250, 100, 250 ],
					"hull": 4,
					"edges": [ 0, 2, 2, 4, 4, 6, 0, 6 ],
					"width": 200,
					"height": 500
				},
				"atk4_3": {
					"type": "mesh",
					"uvs": [ 1, 1, 0, 1, 0, 0, 1, 0 ],
					"triangles": [ 1, 2, 3, 1, 3, 0 ],
					"vertices": [ 100, -250, -100, -250, -100, 250, 100, 250 ],
					"hull": 4,
					"edges": [ 0, 2, 2, 4, 4, 6, 0, 6 ],
					"width": 200,
					"height": 500
				},
				"atk4_5": {
					"type": "mesh",
					"uvs": [ 1, 1, 0, 1, 0, 0, 1, 0 ],
					"triangles": [ 1, 2, 3, 1, 3, 0 ],
					"vertices": [ 100, -250, -100, -250, -100, 250, 100, 250 ],
					"hull": 4,
					"edges": [ 0, 2, 2, 4, 4, 6, 0, 6 ],
					"width": 200,
					"height": 500
				},
				"atk4_7": {
					"type": "mesh",
					"uvs": [ 1, 1, 0, 1, 0, 0, 1, 0 ],
					"triangles": [ 1, 2, 3, 1, 3, 0 ],
					"vertices": [ 100, -250, -100, -250, -100, 250, 100, 250 ],
					"hull": 4,
					"edges": [ 0, 2, 2, 4, 4, 6, 0, 6 ],
					"width": 200,
					"height": 500
				},
				"atk4_9": {
					"type": "mesh",
					"uvs": [ 1, 1, 0, 1, 0, 0, 1, 0 ],
					"triangles": [ 1, 2, 3, 1, 3, 0 ],
					"vertices": [ 100, -250, -100, -250, -100, 250, 100, 250 ],
					"hull": 4,
					"edges": [ 0, 2, 2, 4, 4, 6, 0, 6 ],
					"width": 200,
					"height": 500
				},
				"atk4_11": {
					"type": "mesh",
					"uvs": [ 1, 1, 0, 1, 0, 0, 1, 0 ],
					"triangles": [ 1, 2, 3, 1, 3, 0 ],
					"vertices": [ 100, -250, -100, -250, -100, 250, 100, 250 ],
					"hull": 4,
					"edges": [ 0, 2, 2, 4, 4, 6, 0, 6 ],
					"width": 200,
					"height": 500
				}
			},
			"ss3": {
				"ss1": {
					"type": "mesh",
					"uvs": [ 1, 1, 0, 1, 0, 0, 1, 0 ],
					"triangles": [ 1, 2, 3, 1, 3, 0 ],
					"vertices": [ 144.76, 253.07, 155.17, -246.82, -144.76, -253.07, -155.17, 246.82 ],
					"hull": 4,
					"edges": [ 0, 2, 2, 4, 4, 6, 0, 6 ],
					"width": 500,
					"height": 300
				},
				"ss3": {
					"type": "mesh",
					"uvs": [ 1, 1, 0, 1, 0, 0, 1, 0 ],
					"triangles": [ 1, 2, 3, 1, 3, 0 ],
					"vertices": [ 144.76, 253.07, 155.17, -246.82, -144.76, -253.07, -155.17, 246.82 ],
					"hull": 4,
					"edges": [ 0, 2, 2, 4, 4, 6, 0, 6 ],
					"width": 500,
					"height": 300
				},
				"ss5": {
					"type": "mesh",
					"uvs": [ 1, 1, 0, 1, 0, 0, 1, 0 ],
					"triangles": [ 1, 2, 3, 1, 3, 0 ],
					"vertices": [ 144.76, 253.07, 155.17, -246.82, -144.76, -253.07, -155.17, 246.82 ],
					"hull": 4,
					"edges": [ 0, 2, 2, 4, 4, 6, 0, 6 ],
					"width": 500,
					"height": 300
				},
				"ss7": {
					"type": "mesh",
					"uvs": [ 1, 1, 0, 1, 0, 0, 1, 0 ],
					"triangles": [ 1, 2, 3, 1, 3, 0 ],
					"vertices": [ 144.76, 253.07, 155.17, -246.82, -144.76, -253.07, -155.17, 246.82 ],
					"hull": 4,
					"edges": [ 0, 2, 2, 4, 4, 6, 0, 6 ],
					"width": 500,
					"height": 300
				},
				"ss9": {
					"type": "mesh",
					"uvs": [ 1, 1, 0, 1, 0, 0, 1, 0 ],
					"triangles": [ 1, 2, 3, 1, 3, 0 ],
					"vertices": [ 144.76, 253.07, 155.17, -246.82, -144.76, -253.07, -155.17, 246.82 ],
					"hull": 4,
					"edges": [ 0, 2, 2, 4, 4, 6, 0, 6 ],
					"width": 500,
					"height": 300
				},
				"ss11": {
					"type": "mesh",
					"uvs": [ 1, 1, 0, 1, 0, 0, 1, 0 ],
					"triangles": [ 1, 2, 3, 1, 3, 0 ],
					"vertices": [ 144.76, 253.07, 155.17, -246.82, -144.76, -253.07, -155.17, 246.82 ],
					"hull": 4,
					"edges": [ 0, 2, 2, 4, 4, 6, 0, 6 ],
					"width": 500,
					"height": 300
				}
			},
			"ss4": {
				"ss1": {
					"type": "mesh",
					"uvs": [ 1, 1, 0, 1, 0, 0, 1, 0 ],
					"triangles": [ 1, 2, 3, 1, 3, 0 ],
					"vertices": [ 144.76, 253.07, 155.17, -246.82, -144.76, -253.07, -155.17, 246.82 ],
					"hull": 4,
					"edges": [ 0, 2, 2, 4, 4, 6, 0, 6 ],
					"width": 500,
					"height": 300
				},
				"ss3": {
					"type": "mesh",
					"uvs": [ 1, 1, 0, 1, 0, 0, 1, 0 ],
					"triangles": [ 1, 2, 3, 1, 3, 0 ],
					"vertices": [ 144.76, 253.07, 155.17, -246.82, -144.76, -253.07, -155.17, 246.82 ],
					"hull": 4,
					"edges": [ 0, 2, 2, 4, 4, 6, 0, 6 ],
					"width": 500,
					"height": 300
				},
				"ss5": {
					"type": "mesh",
					"uvs": [ 1, 1, 0, 1, 0, 0, 1, 0 ],
					"triangles": [ 1, 2, 3, 1, 3, 0 ],
					"vertices": [ 144.76, 253.07, 155.17, -246.82, -144.76, -253.07, -155.17, 246.82 ],
					"hull": 4,
					"edges": [ 0, 2, 2, 4, 4, 6, 0, 6 ],
					"width": 500,
					"height": 300
				},
				"ss7": {
					"type": "mesh",
					"uvs": [ 1, 1, 0, 1, 0, 0, 1, 0 ],
					"triangles": [ 1, 2, 3, 1, 3, 0 ],
					"vertices": [ 144.76, 253.07, 155.17, -246.82, -144.76, -253.07, -155.17, 246.82 ],
					"hull": 4,
					"edges": [ 0, 2, 2, 4, 4, 6, 0, 6 ],
					"width": 500,
					"height": 300
				},
				"ss9": {
					"type": "mesh",
					"uvs": [ 1, 1, 0, 1, 0, 0, 1, 0 ],
					"triangles": [ 1, 2, 3, 1, 3, 0 ],
					"vertices": [ 144.76, 253.07, 155.17, -246.82, -144.76, -253.07, -155.17, 246.82 ],
					"hull": 4,
					"edges": [ 0, 2, 2, 4, 4, 6, 0, 6 ],
					"width": 500,
					"height": 300
				},
				"ss11": {
					"type": "mesh",
					"uvs": [ 1, 1, 0, 1, 0, 0, 1, 0 ],
					"triangles": [ 1, 2, 3, 1, 3, 0 ],
					"vertices": [ 144.76, 253.07, 155.17, -246.82, -144.76, -253.07, -155.17, 246.82 ],
					"hull": 4,
					"edges": [ 0, 2, 2, 4, 4, 6, 0, 6 ],
					"width": 500,
					"height": 300
				}
			},
			"ss5": {
				"ss1": {
					"type": "mesh",
					"uvs": [ 1, 1, 0, 1, 0, 0, 1, 0 ],
					"triangles": [ 1, 2, 3, 1, 3, 0 ],
					"vertices": [ 144.76, 253.07, 155.17, -246.82, -144.76, -253.07, -155.17, 246.82 ],
					"hull": 4,
					"edges": [ 0, 2, 2, 4, 4, 6, 0, 6 ],
					"width": 500,
					"height": 300
				},
				"ss3": {
					"type": "mesh",
					"uvs": [ 1, 1, 0, 1, 0, 0, 1, 0 ],
					"triangles": [ 1, 2, 3, 1, 3, 0 ],
					"vertices": [ 144.76, 253.07, 155.17, -246.82, -144.76, -253.07, -155.17, 246.82 ],
					"hull": 4,
					"edges": [ 0, 2, 2, 4, 4, 6, 0, 6 ],
					"width": 500,
					"height": 300
				},
				"ss5": {
					"type": "mesh",
					"uvs": [ 1, 1, 0, 1, 0, 0, 1, 0 ],
					"triangles": [ 1, 2, 3, 1, 3, 0 ],
					"vertices": [ 144.76, 253.07, 155.17, -246.82, -144.76, -253.07, -155.17, 246.82 ],
					"hull": 4,
					"edges": [ 0, 2, 2, 4, 4, 6, 0, 6 ],
					"width": 500,
					"height": 300
				},
				"ss7": {
					"type": "mesh",
					"uvs": [ 1, 1, 0, 1, 0, 0, 1, 0 ],
					"triangles": [ 1, 2, 3, 1, 3, 0 ],
					"vertices": [ 144.76, 253.07, 155.17, -246.82, -144.76, -253.07, -155.17, 246.82 ],
					"hull": 4,
					"edges": [ 0, 2, 2, 4, 4, 6, 0, 6 ],
					"width": 500,
					"height": 300
				},
				"ss9": {
					"type": "mesh",
					"uvs": [ 1, 1, 0, 1, 0, 0, 1, 0 ],
					"triangles": [ 1, 2, 3, 1, 3, 0 ],
					"vertices": [ 144.76, 253.07, 155.17, -246.82, -144.76, -253.07, -155.17, 246.82 ],
					"hull": 4,
					"edges": [ 0, 2, 2, 4, 4, 6, 0, 6 ],
					"width": 500,
					"height": 300
				},
				"ss11": {
					"type": "mesh",
					"uvs": [ 1, 1, 0, 1, 0, 0, 1, 0 ],
					"triangles": [ 1, 2, 3, 1, 3, 0 ],
					"vertices": [ 144.76, 253.07, 155.17, -246.82, -144.76, -253.07, -155.17, 246.82 ],
					"hull": 4,
					"edges": [ 0, 2, 2, 4, 4, 6, 0, 6 ],
					"width": 500,
					"height": 300
				}
			},
			"ss6": {
				"ss1": {
					"type": "mesh",
					"uvs": [ 1, 1, 0, 1, 0, 0, 1, 0 ],
					"triangles": [ 1, 2, 3, 1, 3, 0 ],
					"vertices": [ 144.76, 253.07, 155.17, -246.82, -144.76, -253.07, -155.17, 246.82 ],
					"hull": 4,
					"edges": [ 0, 2, 2, 4, 4, 6, 0, 6 ],
					"width": 500,
					"height": 300
				},
				"ss3": {
					"type": "mesh",
					"uvs": [ 1, 1, 0, 1, 0, 0, 1, 0 ],
					"triangles": [ 1, 2, 3, 1, 3, 0 ],
					"vertices": [ 144.76, 253.07, 155.17, -246.82, -144.76, -253.07, -155.17, 246.82 ],
					"hull": 4,
					"edges": [ 0, 2, 2, 4, 4, 6, 0, 6 ],
					"width": 500,
					"height": 300
				},
				"ss5": {
					"type": "mesh",
					"uvs": [ 1, 1, 0, 1, 0, 0, 1, 0 ],
					"triangles": [ 1, 2, 3, 1, 3, 0 ],
					"vertices": [ 144.76, 253.07, 155.17, -246.82, -144.76, -253.07, -155.17, 246.82 ],
					"hull": 4,
					"edges": [ 0, 2, 2, 4, 4, 6, 0, 6 ],
					"width": 500,
					"height": 300
				},
				"ss7": {
					"type": "mesh",
					"uvs": [ 1, 1, 0, 1, 0, 0, 1, 0 ],
					"triangles": [ 1, 2, 3, 1, 3, 0 ],
					"vertices": [ 144.76, 253.07, 155.17, -246.82, -144.76, -253.07, -155.17, 246.82 ],
					"hull": 4,
					"edges": [ 0, 2, 2, 4, 4, 6, 0, 6 ],
					"width": 500,
					"height": 300
				},
				"ss9": {
					"type": "mesh",
					"uvs": [ 1, 1, 0, 1, 0, 0, 1, 0 ],
					"triangles": [ 1, 2, 3, 1, 3, 0 ],
					"vertices": [ 144.76, 253.07, 155.17, -246.82, -144.76, -253.07, -155.17, 246.82 ],
					"hull": 4,
					"edges": [ 0, 2, 2, 4, 4, 6, 0, 6 ],
					"width": 500,
					"height": 300
				},
				"ss11": {
					"type": "mesh",
					"uvs": [ 1, 1, 0, 1, 0, 0, 1, 0 ],
					"triangles": [ 1, 2, 3, 1, 3, 0 ],
					"vertices": [ 144.76, 253.07, 155.17, -246.82, -144.76, -253.07, -155.17, 246.82 ],
					"hull": 4,
					"edges": [ 0, 2, 2, 4, 4, 6, 0, 6 ],
					"width": 500,
					"height": 300
				}
			},
			"ss7": {
				"ss1": {
					"type": "mesh",
					"uvs": [ 1, 1, 0, 1, 0, 0, 1, 0 ],
					"triangles": [ 1, 2, 3, 1, 3, 0 ],
					"vertices": [ 144.76, 253.07, 155.17, -246.82, -144.76, -253.07, -155.17, 246.82 ],
					"hull": 4,
					"edges": [ 0, 2, 2, 4, 4, 6, 0, 6 ],
					"width": 500,
					"height": 300
				},
				"ss3": {
					"type": "mesh",
					"uvs": [ 1, 1, 0, 1, 0, 0, 1, 0 ],
					"triangles": [ 1, 2, 3, 1, 3, 0 ],
					"vertices": [ 144.76, 253.07, 155.17, -246.82, -144.76, -253.07, -155.17, 246.82 ],
					"hull": 4,
					"edges": [ 0, 2, 2, 4, 4, 6, 0, 6 ],
					"width": 500,
					"height": 300
				},
				"ss5": {
					"type": "mesh",
					"uvs": [ 1, 1, 0, 1, 0, 0, 1, 0 ],
					"triangles": [ 1, 2, 3, 1, 3, 0 ],
					"vertices": [ 144.76, 253.07, 155.17, -246.82, -144.76, -253.07, -155.17, 246.82 ],
					"hull": 4,
					"edges": [ 0, 2, 2, 4, 4, 6, 0, 6 ],
					"width": 500,
					"height": 300
				},
				"ss7": {
					"type": "mesh",
					"uvs": [ 1, 1, 0, 1, 0, 0, 1, 0 ],
					"triangles": [ 1, 2, 3, 1, 3, 0 ],
					"vertices": [ 144.76, 253.07, 155.17, -246.82, -144.76, -253.07, -155.17, 246.82 ],
					"hull": 4,
					"edges": [ 0, 2, 2, 4, 4, 6, 0, 6 ],
					"width": 500,
					"height": 300
				},
				"ss9": {
					"type": "mesh",
					"uvs": [ 1, 1, 0, 1, 0, 0, 1, 0 ],
					"triangles": [ 1, 2, 3, 1, 3, 0 ],
					"vertices": [ 144.76, 253.07, 155.17, -246.82, -144.76, -253.07, -155.17, 246.82 ],
					"hull": 4,
					"edges": [ 0, 2, 2, 4, 4, 6, 0, 6 ],
					"width": 500,
					"height": 300
				},
				"ss11": {
					"type": "mesh",
					"uvs": [ 1, 1, 0, 1, 0, 0, 1, 0 ],
					"triangles": [ 1, 2, 3, 1, 3, 0 ],
					"vertices": [ 144.76, 253.07, 155.17, -246.82, -144.76, -253.07, -155.17, 246.82 ],
					"hull": 4,
					"edges": [ 0, 2, 2, 4, 4, 6, 0, 6 ],
					"width": 500,
					"height": 300
				}
			},
			"ss8": {
				"ss1": {
					"type": "mesh",
					"uvs": [ 1, 1, 0, 1, 0, 0, 1, 0 ],
					"triangles": [ 1, 2, 3, 1, 3, 0 ],
					"vertices": [ 144.76, 253.07, 155.17, -246.82, -144.76, -253.07, -155.17, 246.82 ],
					"hull": 4,
					"edges": [ 0, 2, 2, 4, 4, 6, 0, 6 ],
					"width": 500,
					"height": 300
				},
				"ss3": {
					"type": "mesh",
					"uvs": [ 1, 1, 0, 1, 0, 0, 1, 0 ],
					"triangles": [ 1, 2, 3, 1, 3, 0 ],
					"vertices": [ 144.76, 253.07, 155.17, -246.82, -144.76, -253.07, -155.17, 246.82 ],
					"hull": 4,
					"edges": [ 0, 2, 2, 4, 4, 6, 0, 6 ],
					"width": 500,
					"height": 300
				},
				"ss5": {
					"type": "mesh",
					"uvs": [ 1, 1, 0, 1, 0, 0, 1, 0 ],
					"triangles": [ 1, 2, 3, 1, 3, 0 ],
					"vertices": [ 144.76, 253.07, 155.17, -246.82, -144.76, -253.07, -155.17, 246.82 ],
					"hull": 4,
					"edges": [ 0, 2, 2, 4, 4, 6, 0, 6 ],
					"width": 500,
					"height": 300
				},
				"ss7": {
					"type": "mesh",
					"uvs": [ 1, 1, 0, 1, 0, 0, 1, 0 ],
					"triangles": [ 1, 2, 3, 1, 3, 0 ],
					"vertices": [ 144.76, 253.07, 155.17, -246.82, -144.76, -253.07, -155.17, 246.82 ],
					"hull": 4,
					"edges": [ 0, 2, 2, 4, 4, 6, 0, 6 ],
					"width": 500,
					"height": 300
				},
				"ss9": {
					"type": "mesh",
					"uvs": [ 1, 1, 0, 1, 0, 0, 1, 0 ],
					"triangles": [ 1, 2, 3, 1, 3, 0 ],
					"vertices": [ 144.76, 253.07, 155.17, -246.82, -144.76, -253.07, -155.17, 246.82 ],
					"hull": 4,
					"edges": [ 0, 2, 2, 4, 4, 6, 0, 6 ],
					"width": 500,
					"height": 300
				},
				"ss11": {
					"type": "mesh",
					"uvs": [ 1, 1, 0, 1, 0, 0, 1, 0 ],
					"triangles": [ 1, 2, 3, 1, 3, 0 ],
					"vertices": [ 144.76, 253.07, 155.17, -246.82, -144.76, -253.07, -155.17, 246.82 ],
					"hull": 4,
					"edges": [ 0, 2, 2, 4, 4, 6, 0, 6 ],
					"width": 500,
					"height": 300
				}
			},
			"ss9": {
				"ss1": {
					"type": "mesh",
					"uvs": [ 1, 1, 0, 1, 0, 0, 1, 0 ],
					"triangles": [ 1, 2, 3, 1, 3, 0 ],
					"vertices": [ 144.76, 253.07, 155.17, -246.82, -144.76, -253.07, -155.17, 246.82 ],
					"hull": 4,
					"edges": [ 0, 2, 2, 4, 4, 6, 0, 6 ],
					"width": 500,
					"height": 300
				},
				"ss3": {
					"type": "mesh",
					"uvs": [ 1, 1, 0, 1, 0, 0, 1, 0 ],
					"triangles": [ 1, 2, 3, 1, 3, 0 ],
					"vertices": [ 144.76, 253.07, 155.17, -246.82, -144.76, -253.07, -155.17, 246.82 ],
					"hull": 4,
					"edges": [ 0, 2, 2, 4, 4, 6, 0, 6 ],
					"width": 500,
					"height": 300
				},
				"ss5": {
					"type": "mesh",
					"uvs": [ 1, 1, 0, 1, 0, 0, 1, 0 ],
					"triangles": [ 1, 2, 3, 1, 3, 0 ],
					"vertices": [ 144.76, 253.07, 155.17, -246.82, -144.76, -253.07, -155.17, 246.82 ],
					"hull": 4,
					"edges": [ 0, 2, 2, 4, 4, 6, 0, 6 ],
					"width": 500,
					"height": 300
				},
				"ss7": {
					"type": "mesh",
					"uvs": [ 1, 1, 0, 1, 0, 0, 1, 0 ],
					"triangles": [ 1, 2, 3, 1, 3, 0 ],
					"vertices": [ 144.76, 253.07, 155.17, -246.82, -144.76, -253.07, -155.17, 246.82 ],
					"hull": 4,
					"edges": [ 0, 2, 2, 4, 4, 6, 0, 6 ],
					"width": 500,
					"height": 300
				},
				"ss9": {
					"type": "mesh",
					"uvs": [ 1, 1, 0, 1, 0, 0, 1, 0 ],
					"triangles": [ 1, 2, 3, 1, 3, 0 ],
					"vertices": [ 144.76, 253.07, 155.17, -246.82, -144.76, -253.07, -155.17, 246.82 ],
					"hull": 4,
					"edges": [ 0, 2, 2, 4, 4, 6, 0, 6 ],
					"width": 500,
					"height": 300
				},
				"ss11": {
					"type": "mesh",
					"uvs": [ 1, 1, 0, 1, 0, 0, 1, 0 ],
					"triangles": [ 1, 2, 3, 1, 3, 0 ],
					"vertices": [ 144.76, 253.07, 155.17, -246.82, -144.76, -253.07, -155.17, 246.82 ],
					"hull": 4,
					"edges": [ 0, 2, 2, 4, 4, 6, 0, 6 ],
					"width": 500,
					"height": 300
				}
			},
			"ss10": {
				"ss1": {
					"type": "mesh",
					"uvs": [ 1, 1, 0, 1, 0, 0, 1, 0 ],
					"triangles": [ 1, 2, 3, 1, 3, 0 ],
					"vertices": [ 144.76, 253.07, 155.17, -246.82, -144.76, -253.07, -155.17, 246.82 ],
					"hull": 4,
					"edges": [ 0, 2, 2, 4, 4, 6, 0, 6 ],
					"width": 500,
					"height": 300
				},
				"ss3": {
					"type": "mesh",
					"uvs": [ 1, 1, 0, 1, 0, 0, 1, 0 ],
					"triangles": [ 1, 2, 3, 1, 3, 0 ],
					"vertices": [ 144.76, 253.07, 155.17, -246.82, -144.76, -253.07, -155.17, 246.82 ],
					"hull": 4,
					"edges": [ 0, 2, 2, 4, 4, 6, 0, 6 ],
					"width": 500,
					"height": 300
				},
				"ss5": {
					"type": "mesh",
					"uvs": [ 1, 1, 0, 1, 0, 0, 1, 0 ],
					"triangles": [ 1, 2, 3, 1, 3, 0 ],
					"vertices": [ 144.76, 253.07, 155.17, -246.82, -144.76, -253.07, -155.17, 246.82 ],
					"hull": 4,
					"edges": [ 0, 2, 2, 4, 4, 6, 0, 6 ],
					"width": 500,
					"height": 300
				},
				"ss7": {
					"type": "mesh",
					"uvs": [ 1, 1, 0, 1, 0, 0, 1, 0 ],
					"triangles": [ 1, 2, 3, 1, 3, 0 ],
					"vertices": [ 144.76, 253.07, 155.17, -246.82, -144.76, -253.07, -155.17, 246.82 ],
					"hull": 4,
					"edges": [ 0, 2, 2, 4, 4, 6, 0, 6 ],
					"width": 500,
					"height": 300
				},
				"ss9": {
					"type": "mesh",
					"uvs": [ 1, 1, 0, 1, 0, 0, 1, 0 ],
					"triangles": [ 1, 2, 3, 1, 3, 0 ],
					"vertices": [ 144.76, 253.07, 155.17, -246.82, -144.76, -253.07, -155.17, 246.82 ],
					"hull": 4,
					"edges": [ 0, 2, 2, 4, 4, 6, 0, 6 ],
					"width": 500,
					"height": 300
				},
				"ss11": {
					"type": "mesh",
					"uvs": [ 1, 1, 0, 1, 0, 0, 1, 0 ],
					"triangles": [ 1, 2, 3, 1, 3, 0 ],
					"vertices": [ 144.76, 253.07, 155.17, -246.82, -144.76, -253.07, -155.17, 246.82 ],
					"hull": 4,
					"edges": [ 0, 2, 2, 4, 4, 6, 0, 6 ],
					"width": 500,
					"height": 300
				}
			}
		}
	}
],
"events": {
	"k": {}
},
"animations": {
	"skill293": {
		"slots": {
			"atk3_5": {
				"attachment": [
					{ "name": "x1" },
					{ "time": 0.0667, "name": "x3" },
					{ "time": 0.1333, "name": "x5" },
					{ "time": 0.2, "name": "x7" },
					{ "time": 0.2667, "name": "x9" },
					{ "time": 0.3333, "name": "x11" },
					{ "time": 0.4, "name": "x13" },
					{ "time": 0.4667, "name": null }
				]
			},
			"atk3_6": {
				"color": [
					{ "color": "ffffff8e" }
				],
				"attachment": [
					{ "name": "x1" },
					{ "time": 0.0667, "name": "x3" },
					{ "time": 0.1333, "name": "x5" },
					{ "time": 0.2, "name": "x7" },
					{ "time": 0.2667, "name": "x9" },
					{ "time": 0.3333, "name": "x11" },
					{ "time": 0.4, "name": "x13" },
					{ "time": 0.4667, "name": null }
				]
			},
			"atk3_7": {
				"color": [
					{ "time": 0.4, "color": "ffffffff" },
					{ "time": 0.5333, "color": "ffffff00" }
				],
				"attachment": [
					{ "time": 0.1, "name": "x13" },
					{ "time": 0.1667, "name": "x11" },
					{ "time": 0.2333, "name": "x9" },
					{ "time": 0.3, "name": "x7" },
					{ "time": 0.3667, "name": "x5" },
					{ "time": 0.5, "name": "x1" },
					{ "time": 0.5333, "name": null }
				]
			},
			"atk3_8": {
				"color": [
					{ "time": 0.0667, "color": "ffffff8e", "curve": "stepped" },
					{ "time": 0.4, "color": "ffffff8e" },
					{ "time": 0.5333, "color": "ffffff00" }
				],
				"attachment": [
					{ "time": 0.1, "name": "x13" },
					{ "time": 0.1667, "name": "x11" },
					{ "time": 0.2333, "name": "x9" },
					{ "time": 0.3, "name": "x7" },
					{ "time": 0.3667, "name": "x5" },
					{ "time": 0.4333, "name": "x3" },
					{ "time": 0.5, "name": "x1" },
					{ "time": 0.5333, "name": null }
				]
			},
			"atk3_9": {
				"attachment": [
					{ "time": 0.1333, "name": "x1" },
					{ "time": 0.2, "name": "x3" },
					{ "time": 0.2667, "name": "x5" },
					{ "time": 0.3333, "name": "x7" },
					{ "time": 0.4, "name": "x9" },
					{ "time": 0.4667, "name": "x11" },
					{ "time": 0.5333, "name": "x13" },
					{ "time": 0.6, "name": null }
				]
			},
			"atk3_10": {
				"color": [
					{ "time": 0.1333, "color": "ffffff8e" }
				],
				"attachment": [
					{ "time": 0.1333, "name": "x1" },
					{ "time": 0.2, "name": "x3" },
					{ "time": 0.2667, "name": "x5" },
					{ "time": 0.3333, "name": "x7" },
					{ "time": 0.4, "name": "x9" },
					{ "time": 0.4667, "name": "x11" },
					{ "time": 0.5333, "name": "x13" },
					{ "time": 0.6, "name": null }
				]
			},
			"atk3_11": {
				"color": [
					{ "time": 0.5, "color": "ffffffff" },
					{ "time": 0.6667, "color": "ffffff00" }
				],
				"attachment": [
					{ "time": 0.2, "name": "x14" },
					{ "time": 0.2333, "name": "x13" },
					{ "time": 0.2667, "name": "x12" },
					{ "time": 0.3, "name": "x11" },
					{ "time": 0.3333, "name": "x10" },
					{ "time": 0.3667, "name": "x9" },
					{ "time": 0.4, "name": "x8" },
					{ "time": 0.4333, "name": "x7" },
					{ "time": 0.4667, "name": "x6" },
					{ "time": 0.5, "name": "x5" },
					{ "time": 0.5333, "name": "x4" },
					{ "time": 0.5667, "name": "x2" },
					{ "time": 0.6333, "name": "x1" },
					{ "time": 0.6667, "name": null }
				]
			},
			"atk3_12": {
				"color": [
					{ "time": 0.2, "color": "ffffff8e", "curve": "stepped" },
					{ "time": 0.5, "color": "ffffff8e" },
					{ "time": 0.6667, "color": "ffffff00" }
				],
				"attachment": [
					{ "time": 0.2, "name": "x14" },
					{ "time": 0.2333, "name": "x13" },
					{ "time": 0.2667, "name": "x12" },
					{ "time": 0.3, "name": "x11" },
					{ "time": 0.3333, "name": "x10" },
					{ "time": 0.3667, "name": "x9" },
					{ "time": 0.4, "name": "x8" },
					{ "time": 0.4333, "name": "x7" },
					{ "time": 0.4667, "name": "x6" },
					{ "time": 0.5, "name": "x5" },
					{ "time": 0.5333, "name": "x4" },
					{ "time": 0.5667, "name": "x3" },
					{ "time": 0.6, "name": "x2" },
					{ "time": 0.6333, "name": "x1" },
					{ "time": 0.6667, "name": null }
				]
			},
			"atk4_3": {
				"attachment": [
					{ "name": "atk4_1" },
					{ "time": 0.0667, "name": "atk4_3" },
					{ "time": 0.1333, "name": "atk4_5" },
					{ "time": 0.2, "name": "atk4_7" },
					{ "time": 0.2667, "name": "atk4_9" },
					{ "time": 0.3333, "name": "atk4_11" },
					{ "time": 0.4, "name": null }
				]
			},
			"atk4_4": {
				"color": [
					{ "color": "ffffff76" }
				],
				"attachment": [
					{ "name": "atk4_1" },
					{ "time": 0.0667, "name": "atk4_3" },
					{ "time": 0.1333, "name": "atk4_5" },
					{ "time": 0.2, "name": "atk4_7" },
					{ "time": 0.2667, "name": "atk4_9" },
					{ "time": 0.3333, "name": "atk4_11" },
					{ "time": 0.4, "name": null }
				]
			},
			"ss3": {
				"attachment": [
					{ "name": "ss1" },
					{ "time": 0.0667, "name": "ss3" },
					{ "time": 0.1333, "name": "ss5" },
					{ "time": 0.2, "name": "ss7" },
					{ "time": 0.2667, "name": "ss9" },
					{ "time": 0.3333, "name": "ss11" },
					{ "time": 0.4, "name": null }
				]
			},
			"ss4": {
				"color": [
					{ "color": "ffffff5d" }
				],
				"attachment": [
					{ "name": "ss1" },
					{ "time": 0.0667, "name": "ss3" },
					{ "time": 0.1333, "name": "ss5" },
					{ "time": 0.2, "name": "ss7" },
					{ "time": 0.2667, "name": "ss9" },
					{ "time": 0.3333, "name": "ss11" },
					{ "time": 0.4, "name": null }
				]
			},
			"ss5": {
				"attachment": [
					{ "time": 0.1333, "name": "ss1" },
					{ "time": 0.2, "name": "ss3" },
					{ "time": 0.2667, "name": "ss5" },
					{ "time": 0.3333, "name": "ss7" },
					{ "time": 0.4, "name": "ss9" },
					{ "time": 0.4667, "name": "ss11" },
					{ "time": 0.5333, "name": null }
				]
			},
			"ss6": {
				"color": [
					{ "time": 0.1333, "color": "ffffff5d" }
				],
				"attachment": [
					{ "time": 0.1333, "name": "ss1" },
					{ "time": 0.2, "name": "ss3" },
					{ "time": 0.2667, "name": "ss5" },
					{ "time": 0.3333, "name": "ss7" },
					{ "time": 0.4, "name": "ss9" },
					{ "time": 0.4667, "name": "ss11" },
					{ "time": 0.5333, "name": null }
				]
			},
			"ss7": {
				"attachment": [
					{ "time": 0.0667, "name": "ss1" },
					{ "time": 0.1333, "name": "ss3" },
					{ "time": 0.2, "name": "ss5" },
					{ "time": 0.2667, "name": "ss7" },
					{ "time": 0.3333, "name": "ss9" },
					{ "time": 0.4, "name": "ss11" },
					{ "time": 0.4667, "name": null }
				]
			},
			"ss8": {
				"color": [
					{ "time": 0.0667, "color": "ffffff5d" }
				],
				"attachment": [
					{ "time": 0.0667, "name": "ss1" },
					{ "time": 0.1333, "name": "ss3" },
					{ "time": 0.2, "name": "ss5" },
					{ "time": 0.2667, "name": "ss7" },
					{ "time": 0.3333, "name": "ss9" },
					{ "time": 0.4, "name": "ss11" },
					{ "time": 0.4667, "name": null }
				]
			},
			"ss9": {
				"attachment": [
					{ "time": 0.2, "name": "ss1" },
					{ "time": 0.2667, "name": "ss3" },
					{ "time": 0.3333, "name": "ss5" },
					{ "time": 0.4, "name": "ss7" },
					{ "time": 0.4667, "name": "ss9" },
					{ "time": 0.5333, "name": "ss11" },
					{ "time": 0.6, "name": null }
				]
			},
			"ss10": {
				"color": [
					{ "time": 0.2, "color": "ffffff5d" }
				],
				"attachment": [
					{ "time": 0.2, "name": "ss1" },
					{ "time": 0.2667, "name": "ss3" },
					{ "time": 0.3333, "name": "ss5" },
					{ "time": 0.4, "name": "ss7" },
					{ "time": 0.4667, "name": "ss9" },
					{ "time": 0.5333, "name": "ss11" },
					{ "time": 0.6, "name": null }
				]
			}
		},
		"bones": {
			"atk4_3": {
				"translate": [
					{ "x": 92.49, "y": 103.25 }
				],
				"scale": [
					{ "x": 1.862, "y": 2.086 }
				]
			},
			"atk3_5": {
				"rotate": [
					{ "angle": -3.66 }
				],
				"translate": [
					{ "x": 253.05, "y": -39.78 }
				],
				"scale": [
					{ "x": 0.551, "y": 1.596 }
				]
			},
			"atk3_6": {
				"rotate": [
					{ "angle": -3.66 }
				],
				"translate": [
					{ "x": 253.05, "y": -39.78 }
				],
				"scale": [
					{ "time": 0.0667, "x": 0.551, "y": 1.225 }
				]
			},
			"atk3_7": {
				"rotate": [
					{ "angle": -3.66 }
				],
				"translate": [
					{ "x": 253.05, "y": -39.78 }
				],
				"scale": [
					{ "time": 0.1333, "x": 0.551 }
				]
			},
			"atk3_8": {
				"rotate": [
					{ "angle": -3.66 }
				],
				"translate": [
					{ "x": 253.05, "y": -39.78 }
				],
				"scale": [
					{ "time": 0.2, "x": 0.469, "y": 0.77 }
				]
			},
			"ss3": {
				"rotate": [
					{ "angle": 268.61 }
				],
				"translate": [
					{ "x": 94.48, "y": 81.85 }
				],
				"scale": [
					{ "x": 0.88, "y": 1.355 }
				]
			},
			"ss4": {
				"rotate": [
					{ "time": 0.1333, "angle": 268.61 }
				],
				"translate": [
					{ "time": 0.1333, "x": 143.41, "y": 81.85 }
				]
			},
			"ss5": {
				"rotate": [
					{ "time": 0.0667, "angle": 83.4 }
				],
				"translate": [
					{ "time": 0.0667, "x": 148.67, "y": 81.85 }
				],
				"scale": [
					{ "time": 0.0667, "x": 0.874, "y": 1.119 }
				]
			},
			"ss6": {
				"rotate": [
					{ "time": 0.2, "angle": 83.4 }
				],
				"translate": [
					{ "time": 0.2, "x": 239.16, "y": 81.85 }
				],
				"scale": [
					{ "time": 0.2, "x": 0.719, "y": 0.647 }
				]
			}
		},
		"events": [
			{ "time": 0.4, "name": "k" }
		]
	}
}
}